{
    "1": {
        "id": 275240194,
        "order": 1,
        "state": "complete",
        "round": 1,
        "player1": "Purp-Splosion",
        "player2": "Brute Force (forfeit)",
        "player1_id": 170496581,
        "player1_greenroom": 0,
        "player1_prereq": null,
        "player2_id": 170496582,
        "player2_prereq": null,
        "player2_greenroom": 0,
        "winner": "Purp-Splosion",
        "loser": "Brute Force (forfeit)",
        "updated_at": 1652533354,
        "underway": 0,
        "player1_lastFought": 0,
        "player2_lastFought": 0
    },
    "2": {
        "id": 275240195,
        "order": 2,
        "state": "complete",
        "round": 1,
        "player1": "Osiris",
        "player2": "Emotional Damage",
        "player1_id": 170496565,
        "player1_greenroom": 0,
        "player1_prereq": null,
        "player2_id": 170496599,
        "player2_prereq": null,
        "player2_greenroom": 0,
        "winner": "Osiris",
        "loser": "Emotional Damage",
        "updated_at": 1652542671,
        "underway": 0,
        "player1_lastFought": 0,
        "player2_lastFought": 0
    },
    "3": {
        "id": 275240196,
        "order": 3,
        "state": "complete",
        "round": 1,
        "player1": "Tryangles",
        "player2": "Argon Lights",
        "player1_id": 170496566,
        "player1_greenroom": 0,
        "player1_prereq": null,
        "player2_id": 170496598,
        "player2_prereq": null,
        "player2_greenroom": 0,
        "winner": "Argon Lights",
        "loser": "Tryangles",
        "updated_at": 1652537498,
        "underway": 0,
        "player1_lastFought": 0,
        "player2_lastFought": 0
    },
    "4": {
        "id": 275240197,
        "order": 4,
        "state": "complete",
        "round": 1,
        "player1": "Candy Striker",
        "player2": "Omnivore",
        "player1_id": 170496556,
        "player1_greenroom": 0,
        "player1_prereq": null,
        "player2_id": 170496608,
        "player2_prereq": null,
        "player2_greenroom": 0,
        "winner": "Omnivore",
        "loser": "Candy Striker",
        "updated_at": 1652540492,
        "underway": 0,
        "player1_lastFought": 0,
        "player2_lastFought": 0
    },
    "5": {
        "id": 275240198,
        "order": 5,
        "state": "complete",
        "round": 1,
        "player1": "Data Collector",
        "player2": "Gallo 12",
        "player1_id": 170496577,
        "player1_greenroom": 0,
        "player1_prereq": null,
        "player2_id": 170496551,
        "player2_prereq": null,
        "player2_greenroom": 0,
        "winner": "Gallo 12",
        "loser": "Data Collector",
        "updated_at": 1652541522,
        "underway": 0,
        "player1_lastFought": 0,
        "player2_lastFought": 0
    },
    "6": {
        "id": 275240199,
        "order": 6,
        "state": "complete",
        "round": 1,
        "player1": "Zenith",
        "player2": "Ignis Fatuus",
        "player1_id": 170496557,
        "player1_greenroom": 0,
        "player1_prereq": null,
        "player2_id": 170496607,
        "player2_prereq": null,
        "player2_greenroom": 0,
        "winner": "Zenith",
        "loser": "Ignis Fatuus",
        "updated_at": 1652540607,
        "underway": 0,
        "player1_lastFought": 0,
        "player2_lastFought": 0
    },
    "7": {
        "id": 275240200,
        "order": 7,
        "state": "complete",
        "round": 1,
        "player1": "T3",
        "player2": "Rigatoni",
        "player1_id": 170496573,
        "player1_greenroom": 0,
        "player1_prereq": null,
        "player2_id": 170496591,
        "player2_prereq": null,
        "player2_greenroom": 0,
        "winner": "Rigatoni",
        "loser": "T3",
        "updated_at": 1652542098,
        "underway": 0,
        "player1_lastFought": 0,
        "player2_lastFought": 0
    },
    "8": {
        "id": 275240201,
        "order": 8,
        "state": "complete",
        "round": 1,
        "player1": "First Drink of the Day",
        "player2": "Off Killter",
        "player1_id": 170496578,
        "player1_greenroom": 0,
        "player1_prereq": null,
        "player2_id": 170496586,
        "player2_prereq": null,
        "player2_greenroom": 0,
        "winner": "Off Killter",
        "loser": "First Drink of the Day",
        "updated_at": 1652539628,
        "underway": 0,
        "player1_lastFought": 0,
        "player2_lastFought": 0
    },
    "9": {
        "id": 275240202,
        "order": 9,
        "state": "complete",
        "round": 1,
        "player1": "EREBUS (forfeit)",
        "player2": "Spitfire",
        "player1_id": 170496562,
        "player1_greenroom": 0,
        "player1_prereq": null,
        "player2_id": 170496553,
        "player2_prereq": null,
        "player2_greenroom": 0,
        "winner": "Spitfire",
        "loser": "EREBUS (forfeit)",
        "updated_at": 1652533182,
        "underway": 0,
        "player1_lastFought": 0,
        "player2_lastFought": 0
    },
    "10": {
        "id": 275240203,
        "order": 10,
        "state": "complete",
        "round": 1,
        "player1": "Zesty Hugs",
        "player2": "Remember That One Time (forfeit)",
        "player1_id": 170496569,
        "player1_greenroom": 0,
        "player1_prereq": null,
        "player2_id": 170496595,
        "player2_prereq": null,
        "player2_greenroom": 0,
        "winner": "Zesty Hugs",
        "loser": "Remember That One Time (forfeit)",
        "updated_at": 1652533172,
        "underway": 0,
        "player1_lastFought": 0,
        "player2_lastFought": 0
    },
    "11": {
        "id": 275240204,
        "order": 11,
        "state": "complete",
        "round": 1,
        "player1": "Boomerang",
        "player2": "The Red Death (forfeit)",
        "player1_id": 170496603,
        "player1_greenroom": 0,
        "player1_prereq": null,
        "player2_id": 170656355,
        "player2_prereq": null,
        "player2_greenroom": 0,
        "winner": "Boomerang",
        "loser": "The Red Death (forfeit)",
        "updated_at": 1652542132,
        "underway": 0,
        "player1_lastFought": 0,
        "player2_lastFought": 0
    },
    "12": {
        "id": 275240205,
        "order": 12,
        "state": "complete",
        "round": 1,
        "player1": "Polar Vortex",
        "player2": "Sadder Adder (forfeit)",
        "player1_id": 170496576,
        "player1_greenroom": 0,
        "player1_prereq": null,
        "player2_id": 170496587,
        "player2_prereq": null,
        "player2_greenroom": 0,
        "winner": "Polar Vortex",
        "loser": "Sadder Adder (forfeit)",
        "updated_at": 1652533306,
        "underway": 0,
        "player1_lastFought": 0,
        "player2_lastFought": 0
    },
    "13": {
        "id": 275240206,
        "order": 13,
        "state": "complete",
        "round": 1,
        "player1": "Tale of Three Hams",
        "player2": "Walter (Dead)",
        "player1_id": 170496561,
        "player1_greenroom": 0,
        "player1_prereq": null,
        "player2_id": 170496604,
        "player2_prereq": null,
        "player2_greenroom": 0,
        "winner": "Walter (Dead)",
        "loser": "Tale of Three Hams",
        "updated_at": 1652540170,
        "underway": 0,
        "player1_lastFought": 0,
        "player2_lastFought": 0
    },
    "14": {
        "id": 275240207,
        "order": 14,
        "state": "complete",
        "round": 1,
        "player1": "W I D E S K I P P E R",
        "player2": "Backlash Wave",
        "player1_id": 170496570,
        "player1_greenroom": 0,
        "player1_prereq": null,
        "player2_id": 170496594,
        "player2_prereq": null,
        "player2_greenroom": 0,
        "winner": "Backlash Wave",
        "loser": "W I D E S K I P P E R",
        "updated_at": 1652538635,
        "underway": 0,
        "player1_lastFought": 0,
        "player2_lastFought": 0
    },
    "15": {
        "id": 275240208,
        "order": 15,
        "state": "complete",
        "round": 1,
        "player1": "Graveyard Goddess",
        "player2": "helicoboptochopter",
        "player1_id": 170496580,
        "player1_greenroom": 0,
        "player1_prereq": null,
        "player2_id": 170496583,
        "player2_prereq": null,
        "player2_greenroom": 0,
        "winner": "Graveyard Goddess",
        "loser": "helicoboptochopter",
        "updated_at": 1652540045,
        "underway": 0,
        "player1_lastFought": 0,
        "player2_lastFought": 0
    },
    "16": {
        "id": 275240209,
        "order": 16,
        "state": "complete",
        "round": 1,
        "player1": "Komodo",
        "player2": "Ghoulash (forfeit)",
        "player1_id": 170496564,
        "player1_greenroom": 0,
        "player1_prereq": null,
        "player2_id": 170496600,
        "player2_prereq": null,
        "player2_greenroom": 0,
        "winner": "Komodo",
        "loser": "Ghoulash (forfeit)",
        "updated_at": 1652533320,
        "underway": 0,
        "player1_lastFought": 0,
        "player2_lastFought": 0
    },
    "17": {
        "id": 275240210,
        "order": 17,
        "state": "complete",
        "round": 1,
        "player1": "Scrambled",
        "player2": "Frenemies",
        "player1_id": 170496567,
        "player1_greenroom": 0,
        "player1_prereq": null,
        "player2_id": 170496597,
        "player2_prereq": null,
        "player2_greenroom": 0,
        "winner": "Scrambled",
        "loser": "Frenemies",
        "updated_at": 1652543026,
        "underway": 0,
        "player1_lastFought": 0,
        "player2_lastFought": 0
    },
    "18": {
        "id": 275240211,
        "order": 18,
        "state": "complete",
        "round": 1,
        "player1": "MilkTankette",
        "player2": "Qurultay",
        "player1_id": 170496555,
        "player1_greenroom": 0,
        "player1_prereq": null,
        "player2_id": 170496609,
        "player2_prereq": null,
        "player2_greenroom": 0,
        "winner": "MilkTankette",
        "loser": "Qurultay",
        "updated_at": 1652542656,
        "underway": 0,
        "player1_lastFought": 0,
        "player2_lastFought": 0
    },
    "19": {
        "id": 275240212,
        "order": 19,
        "state": "complete",
        "round": 1,
        "player1": "Bananas For Scale",
        "player2": "Nightshade",
        "player1_id": 170496574,
        "player1_greenroom": 0,
        "player1_prereq": null,
        "player2_id": 170496589,
        "player2_prereq": null,
        "player2_greenroom": 0,
        "winner": "Nightshade",
        "loser": "Bananas For Scale",
        "updated_at": 1652541345,
        "underway": 0,
        "player1_lastFought": 0,
        "player2_lastFought": 0
    },
    "20": {
        "id": 275240213,
        "order": 20,
        "state": "complete",
        "round": 1,
        "player1": "Killer Angel",
        "player2": "Swoop",
        "player1_id": 170496559,
        "player1_greenroom": 0,
        "player1_prereq": null,
        "player2_id": 170496606,
        "player2_prereq": null,
        "player2_greenroom": 0,
        "winner": "Killer Angel",
        "loser": "Swoop",
        "updated_at": 1652538120,
        "underway": 0,
        "player1_lastFought": 0,
        "player2_lastFought": 0
    },
    "21": {
        "id": 275240214,
        "order": 21,
        "state": "complete",
        "round": 1,
        "player1": "Crush (FORFEIT)",
        "player2": "Odachi (forfeit)",
        "player1_id": 170496572,
        "player1_greenroom": 0,
        "player1_prereq": null,
        "player2_id": 170496592,
        "player2_prereq": null,
        "player2_greenroom": 0,
        "winner": "Crush (FORFEIT)",
        "loser": "Odachi (forfeit)",
        "updated_at": 1652533321,
        "underway": 0,
        "player1_lastFought": 0,
        "player2_lastFought": 0
    },
    "22": {
        "id": 275240215,
        "order": 22,
        "state": "complete",
        "round": 1,
        "player1": "Real Genius",
        "player2": "Atom",
        "player1_id": 170496579,
        "player1_greenroom": 0,
        "player1_prereq": null,
        "player2_id": 170496584,
        "player2_prereq": null,
        "player2_greenroom": 0,
        "winner": "Atom",
        "loser": "Real Genius",
        "updated_at": 1652539716,
        "underway": 0,
        "player1_lastFought": 0,
        "player2_lastFought": 0
    },
    "23": {
        "id": 275240216,
        "order": 23,
        "state": "complete",
        "round": 1,
        "player1": "entropy(forfeit)",
        "player2": "Kerruptor (forfeit)",
        "player1_id": 170496563,
        "player1_greenroom": 0,
        "player1_prereq": null,
        "player2_id": 170496602,
        "player2_prereq": null,
        "player2_greenroom": 0,
        "winner": "entropy(forfeit)",
        "loser": "Kerruptor (forfeit)",
        "updated_at": 1652533374,
        "underway": 0,
        "player1_lastFought": 0,
        "player2_lastFought": 0
    },
    "24": {
        "id": 275240217,
        "order": 24,
        "state": "complete",
        "round": 1,
        "player1": "Crashfest",
        "player2": "Scrappy Doo",
        "player1_id": 170496568,
        "player1_greenroom": 0,
        "player1_prereq": null,
        "player2_id": 170496596,
        "player2_prereq": null,
        "player2_greenroom": 0,
        "winner": "Crashfest",
        "loser": "Scrappy Doo",
        "updated_at": 1652537586,
        "underway": 0,
        "player1_lastFought": 0,
        "player2_lastFought": 0
    },
    "25": {
        "id": 275240218,
        "order": 25,
        "state": "complete",
        "round": 1,
        "player1": "Inside Job",
        "player2": "Zip Tide",
        "player1_id": 170496554,
        "player1_greenroom": 0,
        "player1_prereq": null,
        "player2_id": 170496610,
        "player2_prereq": null,
        "player2_greenroom": 0,
        "winner": "Inside Job",
        "loser": "Zip Tide",
        "updated_at": 1652539271,
        "underway": 0,
        "player1_lastFought": 0,
        "player2_lastFought": 0
    },
    "26": {
        "id": 275240219,
        "order": 26,
        "state": "complete",
        "round": 1,
        "player1": "Wake and Bake",
        "player2": "Spotlight",
        "player1_id": 170496575,
        "player1_greenroom": 0,
        "player1_prereq": null,
        "player2_id": 170496588,
        "player2_prereq": null,
        "player2_greenroom": 0,
        "winner": "Wake and Bake",
        "loser": "Spotlight",
        "updated_at": 1652541139,
        "underway": 0,
        "player1_lastFought": 0,
        "player2_lastFought": 0
    },
    "27": {
        "id": 275240220,
        "order": 27,
        "state": "complete",
        "round": 1,
        "player1": "The Wumpus",
        "player2": "Shifty",
        "player1_id": 170496560,
        "player1_greenroom": 0,
        "player1_prereq": null,
        "player2_id": 170496605,
        "player2_prereq": null,
        "player2_greenroom": 0,
        "winner": "Shifty",
        "loser": "The Wumpus",
        "updated_at": 1652538584,
        "underway": 0,
        "player1_lastFought": 0,
        "player2_lastFought": 0
    },
    "28": {
        "id": 275240221,
        "order": 28,
        "state": "complete",
        "round": 1,
        "player1": "Chicken Huffin",
        "player2": "Spiral (forfeit)",
        "player1_id": 170496571,
        "player1_greenroom": 0,
        "player1_prereq": null,
        "player2_id": 170496593,
        "player2_prereq": null,
        "player2_greenroom": 0,
        "winner": "Chicken Huffin",
        "loser": "Spiral (forfeit)",
        "updated_at": 1652533265,
        "underway": 0,
        "player1_lastFought": 0,
        "player2_lastFought": 0
    },
    "41": {
        "id": 275240222,
        "order": 41,
        "state": "complete",
        "round": 2,
        "player1": "Saw Loser: 2 Saw 2 Lose",
        "player2": "Purp-Splosion",
        "player1_id": 170496549,
        "player1_greenroom": 0,
        "player1_prereq": null,
        "player2_id": 170496581,
        "player2_prereq": 275240194,
        "player2_greenroom": 0,
        "winner": "Saw Loser: 2 Saw 2 Lose",
        "loser": "Purp-Splosion",
        "updated_at": 1652543646,
        "underway": 0,
        "player1_lastFought": 0,
        "player2_lastFought": 1652533354
    },
    "42": {
        "id": 275240223,
        "order": 42,
        "state": "complete",
        "round": 2,
        "player1": "Osiris",
        "player2": "Argon Lights",
        "player1_id": 170496565,
        "player1_greenroom": 0,
        "player1_prereq": 275240195,
        "player2_id": 170496598,
        "player2_prereq": 275240196,
        "player2_greenroom": 0,
        "winner": "Argon Lights",
        "loser": "Osiris",
        "updated_at": 1652543172,
        "underway": 0,
        "player1_lastFought": 1652542671,
        "player2_lastFought": 1652537498
    },
    "43": {
        "id": 275240224,
        "order": 43,
        "state": "complete",
        "round": 2,
        "player1": "Omnivore",
        "player2": "Gallo 12",
        "player1_id": 170496608,
        "player1_greenroom": 0,
        "player1_prereq": 275240197,
        "player2_id": 170496551,
        "player2_prereq": 275240198,
        "player2_greenroom": 0,
        "winner": "Omnivore",
        "loser": "Gallo 12",
        "updated_at": 1652544000,
        "underway": 0,
        "player1_lastFought": 1652540492,
        "player2_lastFought": 1652541522
    },
    "44": {
        "id": 275240225,
        "order": 44,
        "state": "complete",
        "round": 2,
        "player1": "Zenith",
        "player2": "Rigatoni",
        "player1_id": 170496557,
        "player1_greenroom": 0,
        "player1_prereq": 275240199,
        "player2_id": 170496591,
        "player2_prereq": 275240200,
        "player2_greenroom": 0,
        "winner": "Zenith",
        "loser": "Rigatoni",
        "updated_at": 1652547560,
        "underway": 0,
        "player1_lastFought": 1652540607,
        "player2_lastFought": 1652542098
    },
    "45": {
        "id": 275240226,
        "order": 45,
        "state": "complete",
        "round": 2,
        "player1": "Bosado (forfit)",
        "player2": "Off Killter",
        "player1_id": 170496552,
        "player1_greenroom": 0,
        "player1_prereq": null,
        "player2_id": 170496586,
        "player2_prereq": 275240201,
        "player2_greenroom": 0,
        "winner": "Off Killter",
        "loser": "Bosado (forfit)",
        "updated_at": 1652541021,
        "underway": 0,
        "player1_lastFought": 0,
        "player2_lastFought": 1652539628
    },
    "46": {
        "id": 275240227,
        "order": 46,
        "state": "complete",
        "round": 2,
        "player1": "Spitfire",
        "player2": "Zesty Hugs",
        "player1_id": 170496553,
        "player1_greenroom": 0,
        "player1_prereq": 275240202,
        "player2_id": 170496569,
        "player2_prereq": 275240203,
        "player2_greenroom": 0,
        "winner": "Spitfire",
        "loser": "Zesty Hugs",
        "updated_at": 1652541981,
        "underway": 0,
        "player1_lastFought": 1652533182,
        "player2_lastFought": 1652533172
    },
    "47": {
        "id": 275240228,
        "order": 47,
        "state": "complete",
        "round": 2,
        "player1": "Boomerang",
        "player2": "Polar Vortex",
        "player1_id": 170496603,
        "player1_greenroom": 0,
        "player1_prereq": 275240204,
        "player2_id": 170496576,
        "player2_prereq": 275240205,
        "player2_greenroom": 0,
        "winner": "Boomerang",
        "loser": "Polar Vortex",
        "updated_at": 1652545646,
        "underway": 0,
        "player1_lastFought": 1652542132,
        "player2_lastFought": 1652533306
    },
    "48": {
        "id": 275240229,
        "order": 48,
        "state": "complete",
        "round": 2,
        "player1": "Walter (Dead)",
        "player2": "Backlash Wave",
        "player1_id": 170496604,
        "player1_greenroom": 0,
        "player1_prereq": 275240206,
        "player2_id": 170496594,
        "player2_prereq": 275240207,
        "player2_greenroom": 0,
        "winner": "Walter (Dead)",
        "loser": "Backlash Wave",
        "updated_at": 1652548429,
        "underway": 0,
        "player1_lastFought": 1652540170,
        "player2_lastFought": 1652538635
    },
    "49": {
        "id": 275240230,
        "order": 49,
        "state": "complete",
        "round": 2,
        "player1": "Hype Train",
        "player2": "Graveyard Goddess",
        "player1_id": 170496590,
        "player1_greenroom": 0,
        "player1_prereq": null,
        "player2_id": 170496580,
        "player2_prereq": 275240208,
        "player2_greenroom": 0,
        "winner": "Graveyard Goddess",
        "loser": "Hype Train",
        "updated_at": 1652546800,
        "underway": 0,
        "player1_lastFought": 0,
        "player2_lastFought": 1652540045
    },
    "50": {
        "id": 275240231,
        "order": 50,
        "state": "complete",
        "round": 2,
        "player1": "Komodo",
        "player2": "Scrambled",
        "player1_id": 170496564,
        "player1_greenroom": 0,
        "player1_prereq": 275240209,
        "player2_id": 170496567,
        "player2_prereq": 275240210,
        "player2_greenroom": 0,
        "winner": "Komodo",
        "loser": "Scrambled",
        "updated_at": 1652548027,
        "underway": 0,
        "player1_lastFought": 1652533320,
        "player2_lastFought": 1652543026
    },
    "51": {
        "id": 275240232,
        "order": 51,
        "state": "complete",
        "round": 2,
        "player1": "MilkTankette",
        "player2": "Nightshade",
        "player1_id": 170496555,
        "player1_greenroom": 0,
        "player1_prereq": 275240211,
        "player2_id": 170496589,
        "player2_prereq": 275240212,
        "player2_greenroom": 0,
        "winner": "Nightshade",
        "loser": "MilkTankette",
        "updated_at": 1652552069,
        "underway": 0,
        "player1_lastFought": 1652542656,
        "player2_lastFought": 1652541345
    },
    "52": {
        "id": 275240233,
        "order": 52,
        "state": "complete",
        "round": 2,
        "player1": "Killer Angel",
        "player2": "Crush (FORFEIT)",
        "player1_id": 170496559,
        "player1_greenroom": 0,
        "player1_prereq": 275240213,
        "player2_id": 170496572,
        "player2_prereq": 275240214,
        "player2_greenroom": 0,
        "winner": "Crush (FORFEIT)",
        "loser": "Killer Angel",
        "updated_at": 1652543125,
        "underway": 0,
        "player1_lastFought": 1652538120,
        "player2_lastFought": 1652533321
    },
    "53": {
        "id": 275240234,
        "order": 53,
        "state": "complete",
        "round": 2,
        "player1": "Ablation",
        "player2": "Atom",
        "player1_id": 170496550,
        "player1_greenroom": 0,
        "player1_prereq": null,
        "player2_id": 170496584,
        "player2_prereq": 275240215,
        "player2_greenroom": 0,
        "winner": "Ablation",
        "loser": "Atom",
        "updated_at": 1652542377,
        "underway": 0,
        "player1_lastFought": 0,
        "player2_lastFought": 1652539716
    },
    "54": {
        "id": 275240235,
        "order": 54,
        "state": "complete",
        "round": 2,
        "player1": "entropy(forfeit)",
        "player2": "Crashfest",
        "player1_id": 170496563,
        "player1_greenroom": 0,
        "player1_prereq": 275240216,
        "player2_id": 170496568,
        "player2_prereq": 275240217,
        "player2_greenroom": 0,
        "winner": "Crashfest",
        "loser": "entropy(forfeit)",
        "updated_at": 1652537646,
        "underway": 0,
        "player1_lastFought": 1652533374,
        "player2_lastFought": 1652537586
    },
    "55": {
        "id": 275240236,
        "order": 55,
        "state": "complete",
        "round": 2,
        "player1": "Inside Job",
        "player2": "Wake and Bake",
        "player1_id": 170496554,
        "player1_greenroom": 0,
        "player1_prereq": 275240218,
        "player2_id": 170496575,
        "player2_prereq": 275240219,
        "player2_greenroom": 0,
        "winner": "Wake and Bake",
        "loser": "Inside Job",
        "updated_at": 1652547709,
        "underway": 0,
        "player1_lastFought": 1652539271,
        "player2_lastFought": 1652541139
    },
    "56": {
        "id": 275240237,
        "order": 56,
        "state": "complete",
        "round": 2,
        "player1": "Shifty",
        "player2": "Chicken Huffin",
        "player1_id": 170496605,
        "player1_greenroom": 0,
        "player1_prereq": 275240220,
        "player2_id": 170496571,
        "player2_prereq": 275240221,
        "player2_greenroom": 0,
        "winner": "Shifty",
        "loser": "Chicken Huffin",
        "updated_at": 1652541312,
        "underway": 0,
        "player1_lastFought": 1652538584,
        "player2_lastFought": 1652533265
    },
    "81": {
        "id": 275240238,
        "order": 81,
        "state": "complete",
        "round": 3,
        "player1": "Saw Loser: 2 Saw 2 Lose",
        "player2": "Argon Lights",
        "player1_id": 170496549,
        "player1_greenroom": 0,
        "player1_prereq": 275240222,
        "player2_id": 170496598,
        "player2_prereq": 275240223,
        "player2_greenroom": 0,
        "winner": "Saw Loser: 2 Saw 2 Lose",
        "loser": "Argon Lights",
        "updated_at": 1652549287,
        "underway": 0,
        "player1_lastFought": 1652543646,
        "player2_lastFought": 1652543172
    },
    "82": {
        "id": 275240239,
        "order": 82,
        "state": "complete",
        "round": 3,
        "player1": "Omnivore",
        "player2": "Zenith",
        "player1_id": 170496608,
        "player1_greenroom": 0,
        "player1_prereq": 275240224,
        "player2_id": 170496557,
        "player2_prereq": 275240225,
        "player2_greenroom": 0,
        "winner": "Omnivore",
        "loser": "Zenith",
        "updated_at": 1652554658,
        "underway": 0,
        "player1_lastFought": 1652544000,
        "player2_lastFought": 1652547560
    },
    "83": {
        "id": 275240240,
        "order": 83,
        "state": "complete",
        "round": 3,
        "player1": "Off Killter",
        "player2": "Spitfire",
        "player1_id": 170496586,
        "player1_greenroom": 0,
        "player1_prereq": 275240226,
        "player2_id": 170496553,
        "player2_prereq": 275240227,
        "player2_greenroom": 0,
        "winner": "Spitfire",
        "loser": "Off Killter",
        "updated_at": 1652554661,
        "underway": 0,
        "player1_lastFought": 1652541021,
        "player2_lastFought": 1652541981
    },
    "84": {
        "id": 275240241,
        "order": 84,
        "state": "complete",
        "round": 3,
        "player1": "Boomerang",
        "player2": "Walter (Dead)",
        "player1_id": 170496603,
        "player1_greenroom": 0,
        "player1_prereq": 275240228,
        "player2_id": 170496604,
        "player2_prereq": 275240229,
        "player2_greenroom": 0,
        "winner": "Walter (Dead)",
        "loser": "Boomerang",
        "updated_at": 1652555341,
        "underway": 0,
        "player1_lastFought": 1652545646,
        "player2_lastFought": 1652548429
    },
    "85": {
        "id": 275240242,
        "order": 85,
        "state": "complete",
        "round": 3,
        "player1": "Graveyard Goddess",
        "player2": "Komodo",
        "player1_id": 170496580,
        "player1_greenroom": 0,
        "player1_prereq": 275240230,
        "player2_id": 170496564,
        "player2_prereq": 275240231,
        "player2_greenroom": 0,
        "winner": "Komodo",
        "loser": "Graveyard Goddess",
        "updated_at": 1652553144,
        "underway": 0,
        "player1_lastFought": 1652546800,
        "player2_lastFought": 1652548027
    },
    "86": {
        "id": 275240243,
        "order": 86,
        "state": "complete",
        "round": 3,
        "player1": "Nightshade",
        "player2": "Crush (FORFEIT)",
        "player1_id": 170496589,
        "player1_greenroom": 0,
        "player1_prereq": 275240232,
        "player2_id": 170496572,
        "player2_prereq": 275240233,
        "player2_greenroom": 0,
        "winner": "Crush (FORFEIT)",
        "loser": "Nightshade",
        "updated_at": 1652554934,
        "underway": 0,
        "player1_lastFought": 1652552069,
        "player2_lastFought": 1652543125
    },
    "87": {
        "id": 275240244,
        "order": 87,
        "state": "complete",
        "round": 3,
        "player1": "Ablation",
        "player2": "Crashfest",
        "player1_id": 170496550,
        "player1_greenroom": 0,
        "player1_prereq": 275240234,
        "player2_id": 170496568,
        "player2_prereq": 275240235,
        "player2_greenroom": 0,
        "winner": "Crashfest",
        "loser": "Ablation",
        "updated_at": 1652548385,
        "underway": 0,
        "player1_lastFought": 1652542377,
        "player2_lastFought": 1652537646
    },
    "88": {
        "id": 275240245,
        "order": 88,
        "state": "complete",
        "round": 3,
        "player1": "Wake and Bake",
        "player2": "Shifty",
        "player1_id": 170496575,
        "player1_greenroom": 0,
        "player1_prereq": 275240236,
        "player2_id": 170496605,
        "player2_prereq": 275240237,
        "player2_greenroom": 0,
        "winner": "Wake and Bake",
        "loser": "Shifty",
        "updated_at": 1652553339,
        "underway": 0,
        "player1_lastFought": 1652547709,
        "player2_lastFought": 1652541312
    },
    "101": {
        "id": 275240246,
        "order": 101,
        "state": "complete",
        "round": 4,
        "player1": "Saw Loser: 2 Saw 2 Lose",
        "player2": "Omnivore",
        "player1_id": 170496549,
        "player1_greenroom": 0,
        "player1_prereq": 275240238,
        "player2_id": 170496608,
        "player2_prereq": 275240239,
        "player2_greenroom": 0,
        "winner": "Saw Loser: 2 Saw 2 Lose",
        "loser": "Omnivore",
        "updated_at": 1652556105,
        "underway": 0,
        "player1_lastFought": 1652549287,
        "player2_lastFought": 1652554658
    },
    "102": {
        "id": 275240247,
        "order": 102,
        "state": "complete",
        "round": 4,
        "player1": "Spitfire",
        "player2": "Walter (Dead)",
        "player1_id": 170496553,
        "player1_greenroom": 0,
        "player1_prereq": 275240240,
        "player2_id": 170496604,
        "player2_prereq": 275240241,
        "player2_greenroom": 0,
        "winner": "Walter (Dead)",
        "loser": "Spitfire",
        "updated_at": 1652561603,
        "underway": 0,
        "player1_lastFought": 1652554661,
        "player2_lastFought": 1652555341
    },
    "103": {
        "id": 275240248,
        "order": 103,
        "state": "complete",
        "round": 4,
        "player1": "Komodo",
        "player2": "Crush (FORFEIT)",
        "player1_id": 170496564,
        "player1_greenroom": 0,
        "player1_prereq": 275240242,
        "player2_id": 170496572,
        "player2_prereq": 275240243,
        "player2_greenroom": 0,
        "winner": "Komodo",
        "loser": "Crush (FORFEIT)",
        "updated_at": 1652559119,
        "underway": 0,
        "player1_lastFought": 1652553144,
        "player2_lastFought": 1652554934
    },
    "104": {
        "id": 275240249,
        "order": 104,
        "state": "complete",
        "round": 4,
        "player1": "Crashfest",
        "player2": "Wake and Bake",
        "player1_id": 170496568,
        "player1_greenroom": 0,
        "player1_prereq": 275240244,
        "player2_id": 170496575,
        "player2_prereq": 275240245,
        "player2_greenroom": 0,
        "winner": "Crashfest",
        "loser": "Wake and Bake",
        "updated_at": 1652556107,
        "underway": 0,
        "player1_lastFought": 1652548385,
        "player2_lastFought": 1652553339
    },
    "111": {
        "id": 275240250,
        "order": 111,
        "state": "complete",
        "round": 5,
        "player1": "Saw Loser: 2 Saw 2 Lose",
        "player2": "Walter (Dead)",
        "player1_id": 170496549,
        "player1_greenroom": 0,
        "player1_prereq": 275240246,
        "player2_id": 170496604,
        "player2_prereq": 275240247,
        "player2_greenroom": 0,
        "winner": "Saw Loser: 2 Saw 2 Lose",
        "loser": "Walter (Dead)",
        "updated_at": 1652564854,
        "underway": 0,
        "player1_lastFought": 1652556105,
        "player2_lastFought": 1652561603
    },
    "112": {
        "id": 275240251,
        "order": 112,
        "state": "complete",
        "round": 5,
        "player1": "Komodo",
        "player2": "Crashfest",
        "player1_id": 170496564,
        "player1_greenroom": 0,
        "player1_prereq": 275240248,
        "player2_id": 170496568,
        "player2_prereq": 275240249,
        "player2_greenroom": 0,
        "winner": "Crashfest",
        "loser": "Komodo",
        "updated_at": 1652561521,
        "underway": 0,
        "player1_lastFought": 1652559119,
        "player2_lastFought": 1652556107
    },
    "116": {
        "id": 275240252,
        "order": 116,
        "state": "complete",
        "round": 6,
        "player1": "Saw Loser: 2 Saw 2 Lose",
        "player2": "Crashfest",
        "player1_id": 170496549,
        "player1_greenroom": 0,
        "player1_prereq": 275240250,
        "player2_id": 170496568,
        "player2_prereq": 275240251,
        "player2_greenroom": 0,
        "winner": "Saw Loser: 2 Saw 2 Lose",
        "loser": "Crashfest",
        "updated_at": 1652571728,
        "underway": 0,
        "player1_lastFought": 1652564854,
        "player2_lastFought": 1652561521
    },
    "29": {
        "id": 275240253,
        "order": 29,
        "state": "complete",
        "round": -1,
        "player1": "Emotional Damage",
        "player2": "Tryangles",
        "player1_id": 170496599,
        "player1_greenroom": 0,
        "player1_prereq": 275240195,
        "player2_id": 170496566,
        "player2_prereq": 275240196,
        "player2_greenroom": 0,
        "winner": "Tryangles",
        "loser": "Emotional Damage",
        "updated_at": 1652549035,
        "underway": 0,
        "player1_lastFought": 1652542671,
        "player2_lastFought": 1652537498
    },
    "30": {
        "id": 275240254,
        "order": 30,
        "state": "complete",
        "round": -1,
        "player1": "Candy Striker",
        "player2": "Data Collector",
        "player1_id": 170496556,
        "player1_greenroom": 0,
        "player1_prereq": 275240197,
        "player2_id": 170496577,
        "player2_prereq": 275240198,
        "player2_greenroom": 0,
        "winner": "Data Collector",
        "loser": "Candy Striker",
        "updated_at": 1652545060,
        "underway": 0,
        "player1_lastFought": 1652540492,
        "player2_lastFought": 1652541522
    },
    "31": {
        "id": 275240255,
        "order": 31,
        "state": "complete",
        "round": -1,
        "player1": "Ignis Fatuus",
        "player2": "T3",
        "player1_id": 170496607,
        "player1_greenroom": 0,
        "player1_prereq": 275240199,
        "player2_id": 170496573,
        "player2_prereq": 275240200,
        "player2_greenroom": 0,
        "winner": "T3",
        "loser": "Ignis Fatuus",
        "updated_at": 1652544514,
        "underway": 0,
        "player1_lastFought": 1652540607,
        "player2_lastFought": 1652542098
    },
    "32": {
        "id": 275240256,
        "order": 32,
        "state": "complete",
        "round": -1,
        "player1": "EREBUS (forfeit)",
        "player2": "Remember That One Time (forfeit)",
        "player1_id": 170496562,
        "player1_greenroom": 0,
        "player1_prereq": 275240202,
        "player2_id": 170496595,
        "player2_prereq": 275240203,
        "player2_greenroom": 0,
        "winner": "Remember That One Time (forfeit)",
        "loser": "EREBUS (forfeit)",
        "updated_at": 1652533273,
        "underway": 0,
        "player1_lastFought": 1652533182,
        "player2_lastFought": 1652533172
    },
    "33": {
        "id": 275240257,
        "order": 33,
        "state": "complete",
        "round": -1,
        "player1": "The Red Death (forfeit)",
        "player2": "Sadder Adder (forfeit)",
        "player1_id": 170656355,
        "player1_greenroom": 0,
        "player1_prereq": 275240204,
        "player2_id": 170496587,
        "player2_prereq": 275240205,
        "player2_greenroom": 0,
        "winner": "The Red Death (forfeit)",
        "loser": "Sadder Adder (forfeit)",
        "updated_at": 1652542464,
        "underway": 0,
        "player1_lastFought": 1652542132,
        "player2_lastFought": 1652533306
    },
    "34": {
        "id": 275240258,
        "order": 34,
        "state": "complete",
        "round": -1,
        "player1": "Tale of Three Hams",
        "player2": "W I D E S K I P P E R",
        "player1_id": 170496561,
        "player1_greenroom": 0,
        "player1_prereq": 275240206,
        "player2_id": 170496570,
        "player2_prereq": 275240207,
        "player2_greenroom": 0,
        "winner": "Tale of Three Hams",
        "loser": "W I D E S K I P P E R",
        "updated_at": 1652545008,
        "underway": 0,
        "player1_lastFought": 1652540170,
        "player2_lastFought": 1652538635
    },
    "35": {
        "id": 275240259,
        "order": 35,
        "state": "complete",
        "round": -1,
        "player1": "Ghoulash (forfeit)",
        "player2": "Frenemies",
        "player1_id": 170496600,
        "player1_greenroom": 0,
        "player1_prereq": 275240209,
        "player2_id": 170496597,
        "player2_prereq": 275240210,
        "player2_greenroom": 0,
        "winner": "Frenemies",
        "loser": "Ghoulash (forfeit)",
        "updated_at": 1652543229,
        "underway": 0,
        "player1_lastFought": 1652533320,
        "player2_lastFought": 1652543026
    },
    "36": {
        "id": 275240260,
        "order": 36,
        "state": "complete",
        "round": -1,
        "player1": "Qurultay",
        "player2": "Bananas For Scale",
        "player1_id": 170496609,
        "player1_greenroom": 0,
        "player1_prereq": 275240211,
        "player2_id": 170496574,
        "player2_prereq": 275240212,
        "player2_greenroom": 0,
        "winner": "Bananas For Scale",
        "loser": "Qurultay",
        "updated_at": 1652546952,
        "underway": 0,
        "player1_lastFought": 1652542656,
        "player2_lastFought": 1652541345
    },
    "37": {
        "id": 275240261,
        "order": 37,
        "state": "complete",
        "round": -1,
        "player1": "Swoop",
        "player2": "Odachi (forfeit)",
        "player1_id": 170496606,
        "player1_greenroom": 0,
        "player1_prereq": 275240213,
        "player2_id": 170496592,
        "player2_prereq": 275240214,
        "player2_greenroom": 0,
        "winner": "Swoop",
        "loser": "Odachi (forfeit)",
        "updated_at": 1652538750,
        "underway": 0,
        "player1_lastFought": 1652538120,
        "player2_lastFought": 1652533321
    },
    "38": {
        "id": 275240262,
        "order": 38,
        "state": "complete",
        "round": -1,
        "player1": "Kerruptor (forfeit)",
        "player2": "Scrappy Doo",
        "player1_id": 170496602,
        "player1_greenroom": 0,
        "player1_prereq": 275240216,
        "player2_id": 170496596,
        "player2_prereq": 275240217,
        "player2_greenroom": 0,
        "winner": "Scrappy Doo",
        "loser": "Kerruptor (forfeit)",
        "updated_at": 1652537658,
        "underway": 0,
        "player1_lastFought": 1652533374,
        "player2_lastFought": 1652537586
    },
    "39": {
        "id": 275240263,
        "order": 39,
        "state": "complete",
        "round": -1,
        "player1": "Zip Tide",
        "player2": "Spotlight",
        "player1_id": 170496610,
        "player1_greenroom": 0,
        "player1_prereq": 275240218,
        "player2_id": 170496588,
        "player2_prereq": 275240219,
        "player2_greenroom": 0,
        "winner": "Spotlight",
        "loser": "Zip Tide",
        "updated_at": 1652547108,
        "underway": 0,
        "player1_lastFought": 1652539271,
        "player2_lastFought": 1652541139
    },
    "40": {
        "id": 275240264,
        "order": 40,
        "state": "complete",
        "round": -1,
        "player1": "The Wumpus",
        "player2": "Spiral (forfeit)",
        "player1_id": 170496560,
        "player1_greenroom": 0,
        "player1_prereq": 275240220,
        "player2_id": 170496593,
        "player2_prereq": 275240221,
        "player2_greenroom": 0,
        "winner": "The Wumpus",
        "loser": "Spiral (forfeit)",
        "updated_at": 1652538753,
        "underway": 0,
        "player1_lastFought": 1652538584,
        "player2_lastFought": 1652533265
    },
    "72": {
        "id": 275240265,
        "order": 72,
        "state": "complete",
        "round": -2,
        "player1": "Chicken Huffin",
        "player2": "Brute Force (forfeit)",
        "player1_id": 170496571,
        "player1_greenroom": 0,
        "player1_prereq": 275240237,
        "player2_id": 170496582,
        "player2_prereq": 275240194,
        "player2_greenroom": 0,
        "winner": "Chicken Huffin",
        "loser": "Brute Force (forfeit)",
        "updated_at": 1652541753,
        "underway": 0,
        "player1_lastFought": 1652541312,
        "player2_lastFought": 1652533354
    },
    "71": {
        "id": 275240266,
        "order": 71,
        "state": "complete",
        "round": -2,
        "player1": "Inside Job",
        "player2": "Tryangles",
        "player1_id": 170496554,
        "player1_greenroom": 0,
        "player1_prereq": 275240236,
        "player2_id": 170496566,
        "player2_prereq": 275240253,
        "player2_greenroom": 0,
        "winner": "Inside Job",
        "loser": "Tryangles",
        "updated_at": 1652551190,
        "underway": 0,
        "player1_lastFought": 1652547709,
        "player2_lastFought": 1652549035
    },
    "70": {
        "id": 275240267,
        "order": 70,
        "state": "complete",
        "round": -2,
        "player1": "entropy(forfeit)",
        "player2": "Data Collector",
        "player1_id": 170496563,
        "player1_greenroom": 0,
        "player1_prereq": 275240235,
        "player2_id": 170496577,
        "player2_prereq": 275240254,
        "player2_greenroom": 0,
        "winner": "Data Collector",
        "loser": "entropy(forfeit)",
        "updated_at": 1652545099,
        "underway": 0,
        "player1_lastFought": 1652537646,
        "player2_lastFought": 1652545060
    },
    "69": {
        "id": 275240268,
        "order": 69,
        "state": "complete",
        "round": -2,
        "player1": "Atom",
        "player2": "T3",
        "player1_id": 170496584,
        "player1_greenroom": 0,
        "player1_prereq": 275240234,
        "player2_id": 170496573,
        "player2_prereq": 275240255,
        "player2_greenroom": 0,
        "winner": "T3",
        "loser": "Atom",
        "updated_at": 1652550437,
        "underway": 0,
        "player1_lastFought": 1652542377,
        "player2_lastFought": 1652544514
    },
    "68": {
        "id": 275240269,
        "order": 68,
        "state": "complete",
        "round": -2,
        "player1": "Killer Angel",
        "player2": "First Drink of the Day",
        "player1_id": 170496559,
        "player1_greenroom": 0,
        "player1_prereq": 275240233,
        "player2_id": 170496578,
        "player2_prereq": 275240201,
        "player2_greenroom": 0,
        "winner": "First Drink of the Day",
        "loser": "Killer Angel",
        "updated_at": 1652548993,
        "underway": 0,
        "player1_lastFought": 1652543125,
        "player2_lastFought": 1652539628
    },
    "67": {
        "id": 275240270,
        "order": 67,
        "state": "complete",
        "round": -2,
        "player1": "MilkTankette",
        "player2": "Remember That One Time (forfeit)",
        "player1_id": 170496555,
        "player1_greenroom": 0,
        "player1_prereq": 275240232,
        "player2_id": 170496595,
        "player2_prereq": 275240256,
        "player2_greenroom": 0,
        "winner": "MilkTankette",
        "loser": "Remember That One Time (forfeit)",
        "updated_at": 1652552328,
        "underway": 0,
        "player1_lastFought": 1652552069,
        "player2_lastFought": 1652533273
    },
    "66": {
        "id": 275240271,
        "order": 66,
        "state": "complete",
        "round": -2,
        "player1": "Scrambled",
        "player2": "The Red Death (forfeit)",
        "player1_id": 170496567,
        "player1_greenroom": 0,
        "player1_prereq": 275240231,
        "player2_id": 170656355,
        "player2_prereq": 275240257,
        "player2_greenroom": 0,
        "winner": "Scrambled",
        "loser": "The Red Death (forfeit)",
        "updated_at": 1652549428,
        "underway": 0,
        "player1_lastFought": 1652548027,
        "player2_lastFought": 1652542464
    },
    "65": {
        "id": 275240272,
        "order": 65,
        "state": "complete",
        "round": -2,
        "player1": "Hype Train",
        "player2": "Tale of Three Hams",
        "player1_id": 170496590,
        "player1_greenroom": 0,
        "player1_prereq": 275240230,
        "player2_id": 170496561,
        "player2_prereq": 275240258,
        "player2_greenroom": 0,
        "winner": "Tale of Three Hams",
        "loser": "Hype Train",
        "updated_at": 1652549820,
        "underway": 0,
        "player1_lastFought": 1652546800,
        "player2_lastFought": 1652545008
    },
    "64": {
        "id": 275240273,
        "order": 64,
        "state": "complete",
        "round": -2,
        "player1": "Backlash Wave",
        "player2": "helicoboptochopter",
        "player1_id": 170496594,
        "player1_greenroom": 0,
        "player1_prereq": 275240229,
        "player2_id": 170496583,
        "player2_prereq": 275240208,
        "player2_greenroom": 0,
        "winner": "Backlash Wave",
        "loser": "helicoboptochopter",
        "updated_at": 1652551471,
        "underway": 0,
        "player1_lastFought": 1652548429,
        "player2_lastFought": 1652540045
    },
    "63": {
        "id": 275240274,
        "order": 63,
        "state": "complete",
        "round": -2,
        "player1": "Polar Vortex",
        "player2": "Frenemies",
        "player1_id": 170496576,
        "player1_greenroom": 0,
        "player1_prereq": 275240228,
        "player2_id": 170496597,
        "player2_prereq": 275240259,
        "player2_greenroom": 0,
        "winner": "Polar Vortex",
        "loser": "Frenemies",
        "updated_at": 1652551727,
        "underway": 0,
        "player1_lastFought": 1652545646,
        "player2_lastFought": 1652543229
    },
    "62": {
        "id": 275240275,
        "order": 62,
        "state": "complete",
        "round": -2,
        "player1": "Zesty Hugs",
        "player2": "Bananas For Scale",
        "player1_id": 170496569,
        "player1_greenroom": 0,
        "player1_prereq": 275240227,
        "player2_id": 170496574,
        "player2_prereq": 275240260,
        "player2_greenroom": 0,
        "winner": "Zesty Hugs",
        "loser": "Bananas For Scale",
        "updated_at": 1652553452,
        "underway": 0,
        "player1_lastFought": 1652541981,
        "player2_lastFought": 1652546952
    },
    "61": {
        "id": 275240276,
        "order": 61,
        "state": "complete",
        "round": -2,
        "player1": "Bosado (forfit)",
        "player2": "Swoop",
        "player1_id": 170496552,
        "player1_greenroom": 0,
        "player1_prereq": 275240226,
        "player2_id": 170496606,
        "player2_prereq": 275240261,
        "player2_greenroom": 0,
        "winner": "Swoop",
        "loser": "Bosado (forfit)",
        "updated_at": 1652541135,
        "underway": 0,
        "player1_lastFought": 1652541021,
        "player2_lastFought": 1652538750
    },
    "60": {
        "id": 275240277,
        "order": 60,
        "state": "complete",
        "round": -2,
        "player1": "Rigatoni",
        "player2": "Real Genius",
        "player1_id": 170496591,
        "player1_greenroom": 0,
        "player1_prereq": 275240225,
        "player2_id": 170496579,
        "player2_prereq": 275240215,
        "player2_greenroom": 0,
        "winner": "Real Genius",
        "loser": "Rigatoni",
        "updated_at": 1652549105,
        "underway": 0,
        "player1_lastFought": 1652547560,
        "player2_lastFought": 1652539716
    },
    "59": {
        "id": 275240278,
        "order": 59,
        "state": "complete",
        "round": -2,
        "player1": "Gallo 12",
        "player2": "Scrappy Doo",
        "player1_id": 170496551,
        "player1_greenroom": 0,
        "player1_prereq": 275240224,
        "player2_id": 170496596,
        "player2_prereq": 275240262,
        "player2_greenroom": 0,
        "winner": "Gallo 12",
        "loser": "Scrappy Doo",
        "updated_at": 1652547943,
        "underway": 0,
        "player1_lastFought": 1652544000,
        "player2_lastFought": 1652537658
    },
    "58": {
        "id": 275240279,
        "order": 58,
        "state": "complete",
        "round": -2,
        "player1": "Osiris",
        "player2": "Spotlight",
        "player1_id": 170496565,
        "player1_greenroom": 0,
        "player1_prereq": 275240223,
        "player2_id": 170496588,
        "player2_prereq": 275240263,
        "player2_greenroom": 0,
        "winner": "Osiris",
        "loser": "Spotlight",
        "updated_at": 1652547481,
        "underway": 0,
        "player1_lastFought": 1652543172,
        "player2_lastFought": 1652547108
    },
    "57": {
        "id": 275240280,
        "order": 57,
        "state": "complete",
        "round": -2,
        "player1": "Purp-Splosion",
        "player2": "The Wumpus",
        "player1_id": 170496581,
        "player1_greenroom": 0,
        "player1_prereq": 275240222,
        "player2_id": 170496560,
        "player2_prereq": 275240264,
        "player2_greenroom": 0,
        "winner": "The Wumpus",
        "loser": "Purp-Splosion",
        "updated_at": 1652553010,
        "underway": 0,
        "player1_lastFought": 1652543646,
        "player2_lastFought": 1652538753
    },
    "80": {
        "id": 275240281,
        "order": 80,
        "state": "complete",
        "round": -3,
        "player1": "Chicken Huffin",
        "player2": "Inside Job",
        "player1_id": 170496571,
        "player1_greenroom": 0,
        "player1_prereq": 275240265,
        "player2_id": 170496554,
        "player2_prereq": 275240266,
        "player2_greenroom": 0,
        "winner": "Inside Job",
        "loser": "Chicken Huffin",
        "updated_at": 1652555603,
        "underway": 0,
        "player1_lastFought": 1652541753,
        "player2_lastFought": 1652551190
    },
    "79": {
        "id": 275240282,
        "order": 79,
        "state": "complete",
        "round": -3,
        "player1": "Data Collector",
        "player2": "T3",
        "player1_id": 170496577,
        "player1_greenroom": 0,
        "player1_prereq": 275240267,
        "player2_id": 170496573,
        "player2_prereq": 275240268,
        "player2_greenroom": 0,
        "winner": "Data Collector",
        "loser": "T3",
        "updated_at": 1652554379,
        "underway": 0,
        "player1_lastFought": 1652545099,
        "player2_lastFought": 1652550437
    },
    "78": {
        "id": 275240283,
        "order": 78,
        "state": "complete",
        "round": -3,
        "player1": "First Drink of the Day",
        "player2": "MilkTankette",
        "player1_id": 170496578,
        "player1_greenroom": 0,
        "player1_prereq": 275240269,
        "player2_id": 170496555,
        "player2_prereq": 275240270,
        "player2_greenroom": 0,
        "winner": "First Drink of the Day",
        "loser": "MilkTankette",
        "updated_at": 1652558012,
        "underway": 0,
        "player1_lastFought": 1652548993,
        "player2_lastFought": 1652552328
    },
    "77": {
        "id": 275240284,
        "order": 77,
        "state": "complete",
        "round": -3,
        "player1": "Scrambled",
        "player2": "Tale of Three Hams",
        "player1_id": 170496567,
        "player1_greenroom": 0,
        "player1_prereq": 275240271,
        "player2_id": 170496561,
        "player2_prereq": 275240272,
        "player2_greenroom": 0,
        "winner": "Scrambled",
        "loser": "Tale of Three Hams",
        "updated_at": 1652554217,
        "underway": 0,
        "player1_lastFought": 1652549428,
        "player2_lastFought": 1652549820
    },
    "76": {
        "id": 275240285,
        "order": 76,
        "state": "complete",
        "round": -3,
        "player1": "Backlash Wave",
        "player2": "Polar Vortex",
        "player1_id": 170496594,
        "player1_greenroom": 0,
        "player1_prereq": 275240273,
        "player2_id": 170496576,
        "player2_prereq": 275240274,
        "player2_greenroom": 0,
        "winner": "Backlash Wave",
        "loser": "Polar Vortex",
        "updated_at": 1652556574,
        "underway": 0,
        "player1_lastFought": 1652551471,
        "player2_lastFought": 1652551727
    },
    "75": {
        "id": 275240286,
        "order": 75,
        "state": "complete",
        "round": -3,
        "player1": "Zesty Hugs",
        "player2": "Swoop",
        "player1_id": 170496569,
        "player1_greenroom": 0,
        "player1_prereq": 275240275,
        "player2_id": 170496606,
        "player2_prereq": 275240276,
        "player2_greenroom": 0,
        "winner": "Zesty Hugs",
        "loser": "Swoop",
        "updated_at": 1652555729,
        "underway": 0,
        "player1_lastFought": 1652553452,
        "player2_lastFought": 1652541135
    },
    "74": {
        "id": 275240287,
        "order": 74,
        "state": "complete",
        "round": -3,
        "player1": "Real Genius",
        "player2": "Gallo 12",
        "player1_id": 170496579,
        "player1_greenroom": 0,
        "player1_prereq": 275240277,
        "player2_id": 170496551,
        "player2_prereq": 275240278,
        "player2_greenroom": 0,
        "winner": "Gallo 12",
        "loser": "Real Genius",
        "updated_at": 1652552617,
        "underway": 0,
        "player1_lastFought": 1652549105,
        "player2_lastFought": 1652547943
    },
    "73": {
        "id": 275240288,
        "order": 73,
        "state": "complete",
        "round": -3,
        "player1": "Osiris",
        "player2": "The Wumpus",
        "player1_id": 170496565,
        "player1_greenroom": 0,
        "player1_prereq": 275240279,
        "player2_id": 170496560,
        "player2_prereq": 275240280,
        "player2_greenroom": 0,
        "winner": "The Wumpus",
        "loser": "Osiris",
        "updated_at": 1652555958,
        "underway": 0,
        "player1_lastFought": 1652547481,
        "player2_lastFought": 1652553010
    },
    "92": {
        "id": 275240289,
        "order": 92,
        "state": "complete",
        "round": -4,
        "player1": "Boomerang",
        "player2": "Inside Job",
        "player1_id": 170496603,
        "player1_greenroom": 0,
        "player1_prereq": 275240241,
        "player2_id": 170496554,
        "player2_prereq": 275240281,
        "player2_greenroom": 0,
        "winner": "Inside Job",
        "loser": "Boomerang",
        "updated_at": 1652559960,
        "underway": 0,
        "player1_lastFought": 1652555341,
        "player2_lastFought": 1652555603
    },
    "91": {
        "id": 275240290,
        "order": 91,
        "state": "complete",
        "round": -4,
        "player1": "Off Killter",
        "player2": "Data Collector",
        "player1_id": 170496586,
        "player1_greenroom": 0,
        "player1_prereq": 275240240,
        "player2_id": 170496577,
        "player2_prereq": 275240282,
        "player2_greenroom": 0,
        "winner": "Data Collector",
        "loser": "Off Killter",
        "updated_at": 1652562879,
        "underway": 0,
        "player1_lastFought": 1652554661,
        "player2_lastFought": 1652554379
    },
    "90": {
        "id": 275240291,
        "order": 90,
        "state": "complete",
        "round": -4,
        "player1": "Zenith",
        "player2": "First Drink of the Day",
        "player1_id": 170496557,
        "player1_greenroom": 0,
        "player1_prereq": 275240239,
        "player2_id": 170496578,
        "player2_prereq": 275240283,
        "player2_greenroom": 0,
        "winner": "First Drink of the Day",
        "loser": "Zenith",
        "updated_at": 1652560722,
        "underway": 0,
        "player1_lastFought": 1652554658,
        "player2_lastFought": 1652558012
    },
    "89": {
        "id": 275240292,
        "order": 89,
        "state": "complete",
        "round": -4,
        "player1": "Argon Lights",
        "player2": "Scrambled",
        "player1_id": 170496598,
        "player1_greenroom": 0,
        "player1_prereq": 275240238,
        "player2_id": 170496567,
        "player2_prereq": 275240284,
        "player2_greenroom": 0,
        "winner": "Scrambled",
        "loser": "Argon Lights",
        "updated_at": 1652559533,
        "underway": 0,
        "player1_lastFought": 1652549287,
        "player2_lastFought": 1652554217
    },
    "96": {
        "id": 275240293,
        "order": 96,
        "state": "complete",
        "round": -4,
        "player1": "Shifty",
        "player2": "Backlash Wave",
        "player1_id": 170496605,
        "player1_greenroom": 0,
        "player1_prereq": 275240245,
        "player2_id": 170496594,
        "player2_prereq": 275240285,
        "player2_greenroom": 0,
        "winner": "Shifty",
        "loser": "Backlash Wave",
        "updated_at": 1652559896,
        "underway": 0,
        "player1_lastFought": 1652553339,
        "player2_lastFought": 1652556574
    },
    "95": {
        "id": 275240294,
        "order": 95,
        "state": "complete",
        "round": -4,
        "player1": "Ablation",
        "player2": "Zesty Hugs",
        "player1_id": 170496550,
        "player1_greenroom": 0,
        "player1_prereq": 275240244,
        "player2_id": 170496569,
        "player2_prereq": 275240286,
        "player2_greenroom": 0,
        "winner": "Ablation",
        "loser": "Zesty Hugs",
        "updated_at": 1652556163,
        "underway": 0,
        "player1_lastFought": 1652548385,
        "player2_lastFought": 1652555729
    },
    "94": {
        "id": 275240295,
        "order": 94,
        "state": "complete",
        "round": -4,
        "player1": "Nightshade",
        "player2": "Gallo 12",
        "player1_id": 170496589,
        "player1_greenroom": 0,
        "player1_prereq": 275240243,
        "player2_id": 170496551,
        "player2_prereq": 275240287,
        "player2_greenroom": 0,
        "winner": "Gallo 12",
        "loser": "Nightshade",
        "updated_at": 1652558183,
        "underway": 0,
        "player1_lastFought": 1652554934,
        "player2_lastFought": 1652552617
    },
    "93": {
        "id": 275240296,
        "order": 93,
        "state": "complete",
        "round": -4,
        "player1": "Graveyard Goddess",
        "player2": "The Wumpus",
        "player1_id": 170496580,
        "player1_greenroom": 0,
        "player1_prereq": 275240242,
        "player2_id": 170496560,
        "player2_prereq": 275240288,
        "player2_greenroom": 0,
        "winner": "Graveyard Goddess",
        "loser": "The Wumpus",
        "updated_at": 1652560523,
        "underway": 0,
        "player1_lastFought": 1652553144,
        "player2_lastFought": 1652555958
    },
    "98": {
        "id": 275240297,
        "order": 98,
        "state": "complete",
        "round": -5,
        "player1": "Inside Job",
        "player2": "Data Collector",
        "player1_id": 170496554,
        "player1_greenroom": 0,
        "player1_prereq": 275240289,
        "player2_id": 170496577,
        "player2_prereq": 275240290,
        "player2_greenroom": 0,
        "winner": "Inside Job",
        "loser": "Data Collector",
        "updated_at": 1652567721,
        "underway": 0,
        "player1_lastFought": 1652559960,
        "player2_lastFought": 1652562879
    },
    "97": {
        "id": 275240298,
        "order": 97,
        "state": "complete",
        "round": -5,
        "player1": "First Drink of the Day",
        "player2": "Scrambled",
        "player1_id": 170496578,
        "player1_greenroom": 0,
        "player1_prereq": 275240291,
        "player2_id": 170496567,
        "player2_prereq": 275240292,
        "player2_greenroom": 0,
        "winner": "First Drink of the Day",
        "loser": "Scrambled",
        "updated_at": 1652563577,
        "underway": 0,
        "player1_lastFought": 1652560722,
        "player2_lastFought": 1652559533
    },
    "100": {
        "id": 275240299,
        "order": 100,
        "state": "complete",
        "round": -5,
        "player1": "Shifty",
        "player2": "Ablation",
        "player1_id": 170496605,
        "player1_greenroom": 0,
        "player1_prereq": 275240293,
        "player2_id": 170496550,
        "player2_prereq": 275240294,
        "player2_greenroom": 0,
        "winner": "Shifty",
        "loser": "Ablation",
        "updated_at": 1652562967,
        "underway": 0,
        "player1_lastFought": 1652559896,
        "player2_lastFought": 1652556163
    },
    "99": {
        "id": 275240300,
        "order": 99,
        "state": "complete",
        "round": -5,
        "player1": "Gallo 12",
        "player2": "Graveyard Goddess",
        "player1_id": 170496551,
        "player1_greenroom": 0,
        "player1_prereq": 275240295,
        "player2_id": 170496580,
        "player2_prereq": 275240296,
        "player2_greenroom": 0,
        "winner": "Gallo 12",
        "loser": "Graveyard Goddess",
        "updated_at": 1652566614,
        "underway": 0,
        "player1_lastFought": 1652558183,
        "player2_lastFought": 1652560523
    },
    "107": {
        "id": 275240301,
        "order": 107,
        "state": "complete",
        "round": -6,
        "player1": "Crush (FORFEIT)",
        "player2": "Inside Job",
        "player1_id": 170496572,
        "player1_greenroom": 0,
        "player1_prereq": 275240248,
        "player2_id": 170496554,
        "player2_prereq": 275240297,
        "player2_greenroom": 0,
        "winner": "Inside Job",
        "loser": "Crush (FORFEIT)",
        "updated_at": 1652567731,
        "underway": 0,
        "player1_lastFought": 1652559119,
        "player2_lastFought": 1652567721
    },
    "108": {
        "id": 275240302,
        "order": 108,
        "state": "complete",
        "round": -6,
        "player1": "Wake and Bake",
        "player2": "First Drink of the Day",
        "player1_id": 170496575,
        "player1_greenroom": 0,
        "player1_prereq": 275240249,
        "player2_id": 170496578,
        "player2_prereq": 275240298,
        "player2_greenroom": 0,
        "winner": "Wake and Bake",
        "loser": "First Drink of the Day",
        "updated_at": 1652567278,
        "underway": 0,
        "player1_lastFought": 1652556107,
        "player2_lastFought": 1652563577
    },
    "105": {
        "id": 275240303,
        "order": 105,
        "state": "complete",
        "round": -6,
        "player1": "Omnivore",
        "player2": "Shifty",
        "player1_id": 170496608,
        "player1_greenroom": 0,
        "player1_prereq": 275240246,
        "player2_id": 170496605,
        "player2_prereq": 275240299,
        "player2_greenroom": 0,
        "winner": "Shifty",
        "loser": "Omnivore",
        "updated_at": 1652565805,
        "underway": 0,
        "player1_lastFought": 1652556105,
        "player2_lastFought": 1652562967
    },
    "106": {
        "id": 275240304,
        "order": 106,
        "state": "complete",
        "round": -6,
        "player1": "Spitfire",
        "player2": "Gallo 12",
        "player1_id": 170496553,
        "player1_greenroom": 0,
        "player1_prereq": 275240247,
        "player2_id": 170496551,
        "player2_prereq": 275240300,
        "player2_greenroom": 0,
        "winner": "Spitfire",
        "loser": "Gallo 12",
        "updated_at": 1652572716,
        "underway": 0,
        "player1_lastFought": 1652561603,
        "player2_lastFought": 1652566614
    },
    "110": {
        "id": 275240305,
        "order": 110,
        "state": "complete",
        "round": -7,
        "player1": "Inside Job",
        "player2": "Wake and Bake",
        "player1_id": 170496554,
        "player1_greenroom": 0,
        "player1_prereq": 275240301,
        "player2_id": 170496575,
        "player2_prereq": 275240302,
        "player2_greenroom": 0,
        "winner": "Wake and Bake",
        "loser": "Inside Job",
        "updated_at": 1652570814,
        "underway": 0,
        "player1_lastFought": 1652567731,
        "player2_lastFought": 1652567278
    },
    "109": {
        "id": 275240306,
        "order": 109,
        "state": "complete",
        "round": -7,
        "player1": "Shifty",
        "player2": "Spitfire",
        "player1_id": 170496605,
        "player1_greenroom": 0,
        "player1_prereq": 275240303,
        "player2_id": 170496553,
        "player2_prereq": 275240304,
        "player2_greenroom": 0,
        "winner": "Shifty",
        "loser": "Spitfire",
        "updated_at": 1652575571,
        "underway": 0,
        "player1_lastFought": 1652565805,
        "player2_lastFought": 1652572716
    },
    "113": {
        "id": 275240307,
        "order": 113,
        "state": "complete",
        "round": -8,
        "player1": "Walter (Dead)",
        "player2": "Wake and Bake",
        "player1_id": 170496604,
        "player1_greenroom": 0,
        "player1_prereq": 275240250,
        "player2_id": 170496575,
        "player2_prereq": 275240305,
        "player2_greenroom": 0,
        "winner": "Wake and Bake",
        "loser": "Walter (Dead)",
        "updated_at": 1652570884,
        "underway": 0,
        "player1_lastFought": 1652564854,
        "player2_lastFought": 1652570814
    },
    "114": {
        "id": 275240308,
        "order": 114,
        "state": "complete",
        "round": -8,
        "player1": "Komodo",
        "player2": "Shifty",
        "player1_id": 170496564,
        "player1_greenroom": 0,
        "player1_prereq": 275240251,
        "player2_id": 170496605,
        "player2_prereq": 275240306,
        "player2_greenroom": 0,
        "winner": "Komodo",
        "loser": "Shifty",
        "updated_at": 1652576651,
        "underway": 0,
        "player1_lastFought": 1652561521,
        "player2_lastFought": 1652575571
    },
    "115": {
        "id": 275240309,
        "order": 115,
        "state": "complete",
        "round": -9,
        "player1": "Wake and Bake",
        "player2": "Komodo",
        "player1_id": 170496575,
        "player1_greenroom": 0,
        "player1_prereq": 275240307,
        "player2_id": 170496564,
        "player2_prereq": 275240308,
        "player2_greenroom": 0,
        "winner": "Komodo",
        "loser": "Wake and Bake",
        "updated_at": 1652578602,
        "underway": 0,
        "player1_lastFought": 1652570884,
        "player2_lastFought": 1652576651
    },
    "117": {
        "id": 275240310,
        "order": 117,
        "state": "complete",
        "round": -10,
        "player1": "Crashfest",
        "player2": "Komodo",
        "player1_id": 170496568,
        "player1_greenroom": 0,
        "player1_prereq": 275240252,
        "player2_id": 170496564,
        "player2_prereq": 275240309,
        "player2_greenroom": 0,
        "winner": "Crashfest",
        "loser": "Komodo",
        "updated_at": 1652580880,
        "underway": 0,
        "player1_lastFought": 1652571728,
        "player2_lastFought": 1652578602
    },
    "118": {
        "id": 275240311,
        "order": 118,
        "state": "complete",
        "round": 7,
        "player1": "Saw Loser: 2 Saw 2 Lose",
        "player2": "Crashfest",
        "player1_id": 170496549,
        "player1_greenroom": 0,
        "player1_prereq": 275240252,
        "player2_id": 170496568,
        "player2_prereq": 275240310,
        "player2_greenroom": 0,
        "winner": "Crashfest",
        "loser": "Saw Loser: 2 Saw 2 Lose",
        "updated_at": 1652582977,
        "underway": 0,
        "player1_lastFought": 1652571728,
        "player2_lastFought": 1652580880
    },
    "119": {
        "id": 275240312,
        "order": 119,
        "state": "complete",
        "round": 7,
        "player1": "Crashfest",
        "player2": "Saw Loser: 2 Saw 2 Lose",
        "player1_id": 170496568,
        "player1_greenroom": 0,
        "player1_prereq": 275240311,
        "player2_id": 170496549,
        "player2_prereq": 275240311,
        "player2_greenroom": 0,
        "winner": "Crashfest",
        "loser": "Saw Loser: 2 Saw 2 Lose",
        "updated_at": 1652584520,
        "underway": 0,
        "player1_lastFought": 1652582977,
        "player2_lastFought": 1652582977
    }
}