{
    "1": {
        "id": 269710509,
        "order": 1,
        "state": "complete",
        "round": 1,
        "player1": "Michael the Robot",
        "player2": "Rachet",
        "player1_id": 166697979,
        "player1_greenroom": 0,
        "player1_prereq": null,
        "player2_id": 166697966,
        "player2_prereq": null,
        "player2_greenroom": 0,
        "winner": "Rachet",
        "loser": "Michael the Robot",
        "updated_at": 1648312604,
        "underway": 0,
        "player1_lastFought": 0,
        "player2_lastFought": 0
    },
    "2": {
        "id": 269710510,
        "order": 2,
        "state": "complete",
        "round": 1,
        "player1": "Copy & Paste Mach 2",
        "player2": "Amen Break",
        "player1_id": 166697949,
        "player1_greenroom": 0,
        "player1_prereq": null,
        "player2_id": 166697982,
        "player2_prereq": null,
        "player2_greenroom": 0,
        "winner": "Amen Break",
        "loser": "Copy & Paste Mach 2",
        "updated_at": 1648306019,
        "underway": 0,
        "player1_lastFought": 0,
        "player2_lastFought": 0
    },
    "3": {
        "id": 269710511,
        "order": 3,
        "state": "complete",
        "round": 1,
        "player1": "PinevictuX",
        "player2": "Saber",
        "player1_id": 166697958,
        "player1_greenroom": 0,
        "player1_prereq": null,
        "player2_id": 166697973,
        "player2_prereq": null,
        "player2_greenroom": 0,
        "winner": "Saber",
        "loser": "PinevictuX",
        "updated_at": 1648310277,
        "underway": 0,
        "player1_lastFought": 0,
        "player2_lastFought": 0
    },
    "4": {
        "id": 269710512,
        "order": 4,
        "state": "complete",
        "round": 1,
        "player1": "Not A Hornet",
        "player2": "DeNiteMare",
        "player1_id": 166697957,
        "player1_greenroom": 0,
        "player1_prereq": null,
        "player2_id": 166697974,
        "player2_prereq": null,
        "player2_greenroom": 0,
        "winner": "DeNiteMare",
        "loser": "Not A Hornet",
        "updated_at": 1648306473,
        "underway": 0,
        "player1_lastFought": 0,
        "player2_lastFought": 0
    },
    "5": {
        "id": 269710513,
        "order": 5,
        "state": "complete",
        "round": 1,
        "player1": "Arr See Saw",
        "player2": "Insomnia",
        "player1_id": 166697962,
        "player1_greenroom": 0,
        "player1_prereq": null,
        "player2_id": 166697969,
        "player2_prereq": null,
        "player2_greenroom": 0,
        "winner": "Arr See Saw",
        "loser": "Insomnia",
        "updated_at": 1648306075,
        "underway": 0,
        "player1_lastFought": 0,
        "player2_lastFought": 0
    },
    "6": {
        "id": 269710514,
        "order": 6,
        "state": "complete",
        "round": 1,
        "player1": "Twisty",
        "player2": "Indecisive Mess",
        "player1_id": 166697952,
        "player1_greenroom": 0,
        "player1_prereq": null,
        "player2_id": 166697976,
        "player2_prereq": null,
        "player2_greenroom": 0,
        "winner": "Twisty",
        "loser": "Indecisive Mess",
        "updated_at": 1648305719,
        "underway": 0,
        "player1_lastFought": 0,
        "player2_lastFought": 0
    },
    "7": {
        "id": 269710515,
        "order": 7,
        "state": "complete",
        "round": 1,
        "player1": "Brent the Brick",
        "player2": "Jenson",
        "player1_id": 166697959,
        "player1_greenroom": 0,
        "player1_prereq": null,
        "player2_id": 166697970,
        "player2_prereq": null,
        "player2_greenroom": 0,
        "winner": "Jenson",
        "loser": "Brent the Brick",
        "updated_at": 1648307144,
        "underway": 0,
        "player1_lastFought": 0,
        "player2_lastFought": 0
    },
    "8": {
        "id": 269710516,
        "order": 8,
        "state": "complete",
        "round": 1,
        "player1": "Hot Pok\u00e9",
        "player2": "Chubby Unicorn",
        "player1_id": 166697953,
        "player1_greenroom": 0,
        "player1_prereq": null,
        "player2_id": 166697977,
        "player2_prereq": null,
        "player2_greenroom": 0,
        "winner": "Chubby Unicorn",
        "loser": "Hot Pok\u00e9",
        "updated_at": 1648308302,
        "underway": 0,
        "player1_lastFought": 0,
        "player2_lastFought": 0
    },
    "9": {
        "id": 269710517,
        "order": 9,
        "state": "complete",
        "round": 1,
        "player1": "V.A.C.0.O.M",
        "player2": "Doctor Frankenpine",
        "player1_id": 166697964,
        "player1_greenroom": 0,
        "player1_prereq": null,
        "player2_id": 166697967,
        "player2_prereq": null,
        "player2_greenroom": 0,
        "winner": "V.A.C.0.O.M",
        "loser": "Doctor Frankenpine",
        "updated_at": 1648308077,
        "underway": 0,
        "player1_lastFought": 0,
        "player2_lastFought": 0
    },
    "10": {
        "id": 269710518,
        "order": 10,
        "state": "complete",
        "round": 1,
        "player1": "Be Careful What You Wish For",
        "player2": "electric sheep",
        "player1_id": 166697950,
        "player1_greenroom": 0,
        "player1_prereq": null,
        "player2_id": 166697981,
        "player2_prereq": null,
        "player2_greenroom": 0,
        "winner": "Be Careful What You Wish For",
        "loser": "electric sheep",
        "updated_at": 1648310775,
        "underway": 0,
        "player1_lastFought": 0,
        "player2_lastFought": 0
    },
    "11": {
        "id": 269710519,
        "order": 11,
        "state": "complete",
        "round": 1,
        "player1": "Titanium Knight",
        "player2": "Voltage",
        "player1_id": 166697960,
        "player1_greenroom": 0,
        "player1_prereq": null,
        "player2_id": 166697972,
        "player2_prereq": null,
        "player2_greenroom": 0,
        "winner": "Titanium Knight",
        "loser": "Voltage",
        "updated_at": 1648310663,
        "underway": 0,
        "player1_lastFought": 0,
        "player2_lastFought": 0
    },
    "12": {
        "id": 269710520,
        "order": 12,
        "state": "complete",
        "round": 1,
        "player1": "Wreckfest",
        "player2": "Weta X",
        "player1_id": 166697955,
        "player1_greenroom": 0,
        "player1_prereq": null,
        "player2_id": 166697965,
        "player2_prereq": null,
        "player2_greenroom": 0,
        "winner": "Weta X",
        "loser": "Wreckfest",
        "updated_at": 1648308041,
        "underway": 0,
        "player1_lastFought": 0,
        "player2_lastFought": 0
    },
    "13": {
        "id": 269710521,
        "order": 13,
        "state": "complete",
        "round": 1,
        "player1": "Tygre Claw",
        "player2": "Katrina",
        "player1_id": 166697963,
        "player1_greenroom": 0,
        "player1_prereq": null,
        "player2_id": 166697968,
        "player2_prereq": null,
        "player2_greenroom": 0,
        "winner": "Tygre Claw",
        "loser": "Katrina",
        "updated_at": 1648309547,
        "underway": 0,
        "player1_lastFought": 0,
        "player2_lastFought": 0
    },
    "14": {
        "id": 269710522,
        "order": 14,
        "state": "complete",
        "round": 1,
        "player1": "Phantom III",
        "player2": "The Chort",
        "player1_id": 166697951,
        "player1_greenroom": 0,
        "player1_prereq": null,
        "player2_id": 166697980,
        "player2_prereq": null,
        "player2_greenroom": 0,
        "winner": "Phantom III",
        "loser": "The Chort",
        "updated_at": 1648307111,
        "underway": 0,
        "player1_lastFought": 0,
        "player2_lastFought": 0
    },
    "15": {
        "id": 269710523,
        "order": 15,
        "state": "complete",
        "round": 1,
        "player1": "Harvester",
        "player2": "Jeyla",
        "player1_id": 166697961,
        "player1_greenroom": 0,
        "player1_prereq": null,
        "player2_id": 166697971,
        "player2_prereq": null,
        "player2_greenroom": 0,
        "winner": "Harvester",
        "loser": "Jeyla",
        "updated_at": 1648306149,
        "underway": 0,
        "player1_lastFought": 0,
        "player2_lastFought": 0
    },
    "16": {
        "id": 269710524,
        "order": 16,
        "state": "complete",
        "round": 1,
        "player1": "Hurt Caboose",
        "player2": "Narcissist",
        "player1_id": 166697954,
        "player1_greenroom": 0,
        "player1_prereq": null,
        "player2_id": 166697975,
        "player2_prereq": null,
        "player2_greenroom": 0,
        "winner": "Narcissist",
        "loser": "Hurt Caboose",
        "updated_at": 1648311070,
        "underway": 0,
        "player1_lastFought": 0,
        "player2_lastFought": 0
    },
    "33": {
        "id": 269710525,
        "order": 33,
        "state": "complete",
        "round": 2,
        "player1": "Eruption",
        "player2": "Rachet",
        "player1_id": 166697903,
        "player1_greenroom": 0,
        "player1_prereq": null,
        "player2_id": 166697966,
        "player2_prereq": 269710509,
        "player2_greenroom": 0,
        "winner": "Rachet",
        "loser": "Eruption",
        "updated_at": 1648313041,
        "underway": 0,
        "player1_lastFought": 0,
        "player2_lastFought": 1648312604
    },
    "17": {
        "id": 269710526,
        "order": 17,
        "state": "complete",
        "round": 2,
        "player1": "Tiefschlag",
        "player2": "Drum Go Dum",
        "player1_id": 166697932,
        "player1_greenroom": 0,
        "player1_prereq": null,
        "player2_id": 166697933,
        "player2_prereq": null,
        "player2_greenroom": 0,
        "winner": "Tiefschlag",
        "loser": "Drum Go Dum",
        "updated_at": 1648307120,
        "underway": 0,
        "player1_lastFought": 0,
        "player2_lastFought": 0
    },
    "34": {
        "id": 269710527,
        "order": 34,
        "state": "complete",
        "round": 2,
        "player1": "Jack Rabbit",
        "player2": "Amen Break",
        "player1_id": 166697909,
        "player1_greenroom": 0,
        "player1_prereq": null,
        "player2_id": 166697982,
        "player2_prereq": 269710510,
        "player2_greenroom": 0,
        "winner": "Jack Rabbit",
        "loser": "Amen Break",
        "updated_at": 1648312635,
        "underway": 0,
        "player1_lastFought": 0,
        "player2_lastFought": 1648306019
    },
    "18": {
        "id": 269710528,
        "order": 18,
        "state": "complete",
        "round": 2,
        "player1": "Jet Lag",
        "player2": "Sea Dragons Roar",
        "player1_id": 166697918,
        "player1_greenroom": 0,
        "player1_prereq": null,
        "player2_id": 166697948,
        "player2_prereq": null,
        "player2_greenroom": 0,
        "winner": "Sea Dragons Roar",
        "loser": "Jet Lag",
        "updated_at": 1648307517,
        "underway": 0,
        "player1_lastFought": 0,
        "player2_lastFought": 0
    },
    "35": {
        "id": 269710529,
        "order": 35,
        "state": "complete",
        "round": 2,
        "player1": "Starchild",
        "player2": "Saber",
        "player1_id": 166697910,
        "player1_greenroom": 0,
        "player1_prereq": null,
        "player2_id": 166697973,
        "player2_prereq": 269710511,
        "player2_greenroom": 0,
        "winner": "Starchild",
        "loser": "Saber",
        "updated_at": 1648315178,
        "underway": 0,
        "player1_lastFought": 0,
        "player2_lastFought": 1648310277
    },
    "19": {
        "id": 269710530,
        "order": 19,
        "state": "complete",
        "round": 2,
        "player1": "Nitro Hornet",
        "player2": "Ti",
        "player1_id": 166697956,
        "player1_greenroom": 0,
        "player1_prereq": null,
        "player2_id": 166697939,
        "player2_prereq": null,
        "player2_greenroom": 0,
        "winner": "Ti",
        "loser": "Nitro Hornet",
        "updated_at": 1648308696,
        "underway": 0,
        "player1_lastFought": 0,
        "player2_lastFought": 0
    },
    "36": {
        "id": 269710531,
        "order": 36,
        "state": "complete",
        "round": 2,
        "player1": "Caldera",
        "player2": "DeNiteMare",
        "player1_id": 166697911,
        "player1_greenroom": 0,
        "player1_prereq": null,
        "player2_id": 166697974,
        "player2_prereq": 269710512,
        "player2_greenroom": 0,
        "winner": "Caldera",
        "loser": "DeNiteMare",
        "updated_at": 1648316972,
        "underway": 0,
        "player1_lastFought": 0,
        "player2_lastFought": 1648306473
    },
    "20": {
        "id": 269710532,
        "order": 20,
        "state": "complete",
        "round": 2,
        "player1": "Wicked Wedge",
        "player2": "PGF",
        "player1_id": 166697925,
        "player1_greenroom": 0,
        "player1_prereq": null,
        "player2_id": 166697941,
        "player2_prereq": null,
        "player2_greenroom": 0,
        "winner": "Wicked Wedge",
        "loser": "PGF",
        "updated_at": 1648310033,
        "underway": 0,
        "player1_lastFought": 0,
        "player2_lastFought": 0
    },
    "37": {
        "id": 269710533,
        "order": 37,
        "state": "complete",
        "round": 2,
        "player1": "Red Hawk",
        "player2": "Arr See Saw",
        "player1_id": 166697906,
        "player1_greenroom": 0,
        "player1_prereq": null,
        "player2_id": 166697962,
        "player2_prereq": 269710513,
        "player2_greenroom": 0,
        "winner": "Red Hawk",
        "loser": "Arr See Saw",
        "updated_at": 1648313616,
        "underway": 0,
        "player1_lastFought": 0,
        "player2_lastFought": 1648306075
    },
    "21": {
        "id": 269710534,
        "order": 21,
        "state": "complete",
        "round": 2,
        "player1": "Razor Storm",
        "player2": "Apex",
        "player1_id": 166697929,
        "player1_greenroom": 0,
        "player1_prereq": null,
        "player2_id": 166697936,
        "player2_prereq": null,
        "player2_greenroom": 0,
        "winner": "Apex",
        "loser": "Razor Storm",
        "updated_at": 1648308631,
        "underway": 0,
        "player1_lastFought": 0,
        "player2_lastFought": 0
    },
    "38": {
        "id": 269710535,
        "order": 38,
        "state": "complete",
        "round": 2,
        "player1": "Black Adder",
        "player2": "Twisty",
        "player1_id": 166697914,
        "player1_greenroom": 0,
        "player1_prereq": null,
        "player2_id": 166697952,
        "player2_prereq": 269710514,
        "player2_greenroom": 0,
        "winner": "Twisty",
        "loser": "Black Adder",
        "updated_at": 1648313439,
        "underway": 0,
        "player1_lastFought": 0,
        "player2_lastFought": 1648305719
    },
    "22": {
        "id": 269710536,
        "order": 22,
        "state": "complete",
        "round": 2,
        "player1": "Jack Move",
        "player2": "Ratfish",
        "player1_id": 166697921,
        "player1_greenroom": 0,
        "player1_prereq": null,
        "player2_id": 166697945,
        "player2_prereq": null,
        "player2_greenroom": 0,
        "winner": "Jack Move",
        "loser": "Ratfish",
        "updated_at": 1648308837,
        "underway": 0,
        "player1_lastFought": 0,
        "player2_lastFought": 0
    },
    "39": {
        "id": 269710537,
        "order": 39,
        "state": "complete",
        "round": 2,
        "player1": "Sepi01",
        "player2": "Jenson",
        "player1_id": 166697915,
        "player1_greenroom": 0,
        "player1_prereq": null,
        "player2_id": 166697970,
        "player2_prereq": 269710515,
        "player2_greenroom": 0,
        "winner": "Sepi01",
        "loser": "Jenson",
        "updated_at": 1648313373,
        "underway": 0,
        "player1_lastFought": 0,
        "player2_lastFought": 1648307144
    },
    "23": {
        "id": 269710538,
        "order": 23,
        "state": "complete",
        "round": 2,
        "player1": "LuxRay Mega X",
        "player2": "ER Stingray",
        "player1_id": 166697928,
        "player1_greenroom": 0,
        "player1_prereq": null,
        "player2_id": 166697937,
        "player2_prereq": null,
        "player2_greenroom": 0,
        "winner": "LuxRay Mega X",
        "loser": "ER Stingray",
        "updated_at": 1648309950,
        "underway": 0,
        "player1_lastFought": 0,
        "player2_lastFought": 0
    },
    "40": {
        "id": 269710539,
        "order": 40,
        "state": "complete",
        "round": 2,
        "player1": "Yes Chef Classic",
        "player2": "Chubby Unicorn",
        "player1_id": 166697913,
        "player1_greenroom": 0,
        "player1_prereq": null,
        "player2_id": 166697977,
        "player2_prereq": 269710516,
        "player2_greenroom": 0,
        "winner": "Yes Chef Classic",
        "loser": "Chubby Unicorn",
        "updated_at": 1648314615,
        "underway": 0,
        "player1_lastFought": 0,
        "player2_lastFought": 1648308302
    },
    "24": {
        "id": 269710540,
        "order": 24,
        "state": "complete",
        "round": 2,
        "player1": "Stoneforge",
        "player2": "Pensive Prosciutto",
        "player1_id": 166697922,
        "player1_greenroom": 0,
        "player1_prereq": null,
        "player2_id": 166697943,
        "player2_prereq": null,
        "player2_greenroom": 0,
        "winner": "Stoneforge",
        "loser": "Pensive Prosciutto",
        "updated_at": 1648311601,
        "underway": 0,
        "player1_lastFought": 0,
        "player2_lastFought": 0
    },
    "41": {
        "id": 269710541,
        "order": 41,
        "state": "complete",
        "round": 2,
        "player1": "Adrift",
        "player2": "V.A.C.0.O.M",
        "player1_id": 166697916,
        "player1_greenroom": 0,
        "player1_prereq": null,
        "player2_id": 166697964,
        "player2_prereq": 269710517,
        "player2_greenroom": 0,
        "winner": "Adrift",
        "loser": "V.A.C.0.O.M",
        "updated_at": 1648313538,
        "underway": 0,
        "player1_lastFought": 0,
        "player2_lastFought": 1648308077
    },
    "25": {
        "id": 269710542,
        "order": 25,
        "state": "complete",
        "round": 2,
        "player1": "Fallout",
        "player2": "Voxel v.1",
        "player1_id": 166697931,
        "player1_greenroom": 0,
        "player1_prereq": null,
        "player2_id": 166697934,
        "player2_prereq": null,
        "player2_greenroom": 0,
        "winner": "Voxel v.1",
        "loser": "Fallout",
        "updated_at": 1648312477,
        "underway": 0,
        "player1_lastFought": 0,
        "player2_lastFought": 0
    },
    "42": {
        "id": 269710543,
        "order": 42,
        "state": "complete",
        "round": 2,
        "player1": "Shreddit Bro",
        "player2": "Be Careful What You Wish For",
        "player1_id": 166697904,
        "player1_greenroom": 0,
        "player1_prereq": null,
        "player2_id": 166697950,
        "player2_prereq": 269710518,
        "player2_greenroom": 0,
        "winner": "Shreddit Bro",
        "loser": "Be Careful What You Wish For",
        "updated_at": 1648316841,
        "underway": 0,
        "player1_lastFought": 0,
        "player2_lastFought": 1648310775
    },
    "26": {
        "id": 269710544,
        "order": 26,
        "state": "complete",
        "round": 2,
        "player1": "War? Hard!",
        "player2": "The Shrew",
        "player1_id": 166697919,
        "player1_greenroom": 0,
        "player1_prereq": null,
        "player2_id": 166697947,
        "player2_prereq": null,
        "player2_greenroom": 0,
        "winner": "War? Hard!",
        "loser": "The Shrew",
        "updated_at": 1648310736,
        "underway": 0,
        "player1_lastFought": 0,
        "player2_lastFought": 0
    },
    "43": {
        "id": 269710545,
        "order": 43,
        "state": "complete",
        "round": 2,
        "player1": "Diamondback",
        "player2": "Titanium Knight",
        "player1_id": 166697917,
        "player1_greenroom": 0,
        "player1_prereq": null,
        "player2_id": 166697960,
        "player2_prereq": 269710519,
        "player2_greenroom": 0,
        "winner": "Diamondback",
        "loser": "Titanium Knight",
        "updated_at": 1648314355,
        "underway": 0,
        "player1_lastFought": 0,
        "player2_lastFought": 1648310663
    },
    "27": {
        "id": 269710546,
        "order": 27,
        "state": "complete",
        "round": 2,
        "player1": "ZZ Bot",
        "player2": "Kalma",
        "player1_id": 166697926,
        "player1_greenroom": 0,
        "player1_prereq": null,
        "player2_id": 166697940,
        "player2_prereq": null,
        "player2_greenroom": 0,
        "winner": "Kalma",
        "loser": "ZZ Bot",
        "updated_at": 1648309433,
        "underway": 0,
        "player1_lastFought": 0,
        "player2_lastFought": 0
    },
    "44": {
        "id": 269710547,
        "order": 44,
        "state": "complete",
        "round": 2,
        "player1": "Blackbird",
        "player2": "Weta X",
        "player1_id": 166697912,
        "player1_greenroom": 0,
        "player1_prereq": null,
        "player2_id": 166697965,
        "player2_prereq": 269710520,
        "player2_greenroom": 0,
        "winner": "Weta X",
        "loser": "Blackbird",
        "updated_at": 1648314816,
        "underway": 0,
        "player1_lastFought": 0,
        "player2_lastFought": 1648308041
    },
    "28": {
        "id": 269710548,
        "order": 28,
        "state": "complete",
        "round": 2,
        "player1": "Djem So",
        "player2": "Wormhole",
        "player1_id": 166697924,
        "player1_greenroom": 0,
        "player1_prereq": null,
        "player2_id": 166697942,
        "player2_prereq": null,
        "player2_greenroom": 0,
        "winner": "Djem So",
        "loser": "Wormhole",
        "updated_at": 1648311819,
        "underway": 0,
        "player1_lastFought": 0,
        "player2_lastFought": 0
    },
    "45": {
        "id": 269710549,
        "order": 45,
        "state": "complete",
        "round": 2,
        "player1": "Fully Defined",
        "player2": "Tygre Claw",
        "player1_id": 166846904,
        "player1_greenroom": 0,
        "player1_prereq": null,
        "player2_id": 166697963,
        "player2_prereq": 269710521,
        "player2_greenroom": 0,
        "winner": "Fully Defined",
        "loser": "Tygre Claw",
        "updated_at": 1648315900,
        "underway": 0,
        "player1_lastFought": 0,
        "player2_lastFought": 1648309547
    },
    "29": {
        "id": 269710550,
        "order": 29,
        "state": "complete",
        "round": 2,
        "player1": "Division",
        "player2": "Professor Hex",
        "player1_id": 166697930,
        "player1_greenroom": 0,
        "player1_prereq": null,
        "player2_id": 166697935,
        "player2_prereq": null,
        "player2_greenroom": 0,
        "winner": "Division",
        "loser": "Professor Hex",
        "updated_at": 1648310589,
        "underway": 0,
        "player1_lastFought": 0,
        "player2_lastFought": 0
    },
    "46": {
        "id": 269710551,
        "order": 46,
        "state": "complete",
        "round": 2,
        "player1": "Silk",
        "player2": "Phantom III",
        "player1_id": 166697907,
        "player1_greenroom": 0,
        "player1_prereq": null,
        "player2_id": 166697951,
        "player2_prereq": 269710522,
        "player2_greenroom": 0,
        "winner": "Silk",
        "loser": "Phantom III",
        "updated_at": 1648314264,
        "underway": 0,
        "player1_lastFought": 0,
        "player2_lastFought": 1648307111
    },
    "30": {
        "id": 269710552,
        "order": 30,
        "state": "complete",
        "round": 2,
        "player1": "Spartan X",
        "player2": "The Immortal 'Crixus'",
        "player1_id": 166697920,
        "player1_greenroom": 0,
        "player1_prereq": null,
        "player2_id": 166697946,
        "player2_prereq": null,
        "player2_greenroom": 0,
        "winner": "The Immortal 'Crixus'",
        "loser": "Spartan X",
        "updated_at": 1648310487,
        "underway": 0,
        "player1_lastFought": 0,
        "player2_lastFought": 0
    },
    "47": {
        "id": 269710553,
        "order": 47,
        "state": "complete",
        "round": 2,
        "player1": "Voxel",
        "player2": "Harvester",
        "player1_id": 166697908,
        "player1_greenroom": 0,
        "player1_prereq": null,
        "player2_id": 166697961,
        "player2_prereq": 269710523,
        "player2_greenroom": 0,
        "winner": "Voxel",
        "loser": "Harvester",
        "updated_at": 1648315303,
        "underway": 0,
        "player1_lastFought": 0,
        "player2_lastFought": 1648306149
    },
    "31": {
        "id": 269710554,
        "order": 31,
        "state": "complete",
        "round": 2,
        "player1": "Taurine",
        "player2": "Clyde",
        "player1_id": 166697927,
        "player1_greenroom": 0,
        "player1_prereq": null,
        "player2_id": 166697938,
        "player2_prereq": null,
        "player2_greenroom": 0,
        "winner": "Clyde",
        "loser": "Taurine",
        "updated_at": 1648307161,
        "underway": 0,
        "player1_lastFought": 0,
        "player2_lastFought": 0
    },
    "48": {
        "id": 269710555,
        "order": 48,
        "state": "complete",
        "round": 2,
        "player1": "Silent Spring",
        "player2": "Narcissist",
        "player1_id": 166697905,
        "player1_greenroom": 0,
        "player1_prereq": null,
        "player2_id": 166697975,
        "player2_prereq": 269710524,
        "player2_greenroom": 0,
        "winner": "Silent Spring",
        "loser": "Narcissist",
        "updated_at": 1648316203,
        "underway": 0,
        "player1_lastFought": 0,
        "player2_lastFought": 1648311070
    },
    "32": {
        "id": 269710556,
        "order": 32,
        "state": "complete",
        "round": 2,
        "player1": "Tothik",
        "player2": "Da Dum Tsss",
        "player1_id": 166697923,
        "player1_greenroom": 0,
        "player1_prereq": null,
        "player2_id": 166697944,
        "player2_prereq": null,
        "player2_greenroom": 0,
        "winner": "Tothik",
        "loser": "Da Dum Tsss",
        "updated_at": 1648306686,
        "underway": 0,
        "player1_lastFought": 0,
        "player2_lastFought": 0
    },
    "81": {
        "id": 269710557,
        "order": 81,
        "state": "complete",
        "round": 3,
        "player1": "Rachet",
        "player2": "Tiefschlag",
        "player1_id": 166697966,
        "player1_greenroom": 0,
        "player1_prereq": 269710525,
        "player2_id": 166697932,
        "player2_prereq": 269710526,
        "player2_greenroom": 0,
        "winner": "Tiefschlag",
        "loser": "Rachet",
        "updated_at": 1648321341,
        "underway": 0,
        "player1_lastFought": 1648313041,
        "player2_lastFought": 1648307120
    },
    "82": {
        "id": 269710558,
        "order": 82,
        "state": "complete",
        "round": 3,
        "player1": "Jack Rabbit",
        "player2": "Sea Dragons Roar",
        "player1_id": 166697909,
        "player1_greenroom": 0,
        "player1_prereq": 269710527,
        "player2_id": 166697948,
        "player2_prereq": 269710528,
        "player2_greenroom": 0,
        "winner": "Sea Dragons Roar",
        "loser": "Jack Rabbit",
        "updated_at": 1648323651,
        "underway": 0,
        "player1_lastFought": 1648312635,
        "player2_lastFought": 1648307517
    },
    "83": {
        "id": 269710559,
        "order": 83,
        "state": "complete",
        "round": 3,
        "player1": "Starchild",
        "player2": "Ti",
        "player1_id": 166697910,
        "player1_greenroom": 0,
        "player1_prereq": 269710529,
        "player2_id": 166697939,
        "player2_prereq": 269710530,
        "player2_greenroom": 0,
        "winner": "Starchild",
        "loser": "Ti",
        "updated_at": 1648325287,
        "underway": 0,
        "player1_lastFought": 1648315178,
        "player2_lastFought": 1648308696
    },
    "84": {
        "id": 269710560,
        "order": 84,
        "state": "complete",
        "round": 3,
        "player1": "Caldera",
        "player2": "Wicked Wedge",
        "player1_id": 166697911,
        "player1_greenroom": 0,
        "player1_prereq": 269710531,
        "player2_id": 166697925,
        "player2_prereq": 269710532,
        "player2_greenroom": 0,
        "winner": "Caldera",
        "loser": "Wicked Wedge",
        "updated_at": 1648322334,
        "underway": 0,
        "player1_lastFought": 1648316972,
        "player2_lastFought": 1648310033
    },
    "85": {
        "id": 269710561,
        "order": 85,
        "state": "complete",
        "round": 3,
        "player1": "Red Hawk",
        "player2": "Apex",
        "player1_id": 166697906,
        "player1_greenroom": 0,
        "player1_prereq": 269710533,
        "player2_id": 166697936,
        "player2_prereq": 269710534,
        "player2_greenroom": 0,
        "winner": "Red Hawk",
        "loser": "Apex",
        "updated_at": 1648321410,
        "underway": 0,
        "player1_lastFought": 1648313616,
        "player2_lastFought": 1648308631
    },
    "86": {
        "id": 269710562,
        "order": 86,
        "state": "complete",
        "round": 3,
        "player1": "Twisty",
        "player2": "Jack Move",
        "player1_id": 166697952,
        "player1_greenroom": 0,
        "player1_prereq": 269710535,
        "player2_id": 166697921,
        "player2_prereq": 269710536,
        "player2_greenroom": 0,
        "winner": "Jack Move",
        "loser": "Twisty",
        "updated_at": 1648322018,
        "underway": 0,
        "player1_lastFought": 1648313439,
        "player2_lastFought": 1648308837
    },
    "87": {
        "id": 269710563,
        "order": 87,
        "state": "complete",
        "round": 3,
        "player1": "Sepi01",
        "player2": "LuxRay Mega X",
        "player1_id": 166697915,
        "player1_greenroom": 0,
        "player1_prereq": 269710537,
        "player2_id": 166697928,
        "player2_prereq": 269710538,
        "player2_greenroom": 0,
        "winner": "Sepi01",
        "loser": "LuxRay Mega X",
        "updated_at": 1648323570,
        "underway": 0,
        "player1_lastFought": 1648313373,
        "player2_lastFought": 1648309950
    },
    "88": {
        "id": 269710564,
        "order": 88,
        "state": "complete",
        "round": 3,
        "player1": "Yes Chef Classic",
        "player2": "Stoneforge",
        "player1_id": 166697913,
        "player1_greenroom": 0,
        "player1_prereq": 269710539,
        "player2_id": 166697922,
        "player2_prereq": 269710540,
        "player2_greenroom": 0,
        "winner": "Stoneforge",
        "loser": "Yes Chef Classic",
        "updated_at": 1648324556,
        "underway": 0,
        "player1_lastFought": 1648314615,
        "player2_lastFought": 1648311601
    },
    "89": {
        "id": 269710565,
        "order": 89,
        "state": "complete",
        "round": 3,
        "player1": "Adrift",
        "player2": "Voxel v.1",
        "player1_id": 166697916,
        "player1_greenroom": 0,
        "player1_prereq": 269710541,
        "player2_id": 166697934,
        "player2_prereq": 269710542,
        "player2_greenroom": 0,
        "winner": "Adrift",
        "loser": "Voxel v.1",
        "updated_at": 1648324679,
        "underway": 0,
        "player1_lastFought": 1648313538,
        "player2_lastFought": 1648312477
    },
    "90": {
        "id": 269710566,
        "order": 90,
        "state": "complete",
        "round": 3,
        "player1": "Shreddit Bro",
        "player2": "War? Hard!",
        "player1_id": 166697904,
        "player1_greenroom": 0,
        "player1_prereq": 269710543,
        "player2_id": 166697919,
        "player2_prereq": 269710544,
        "player2_greenroom": 0,
        "winner": "Shreddit Bro",
        "loser": "War? Hard!",
        "updated_at": 1648326605,
        "underway": 0,
        "player1_lastFought": 1648316841,
        "player2_lastFought": 1648310736
    },
    "91": {
        "id": 269710567,
        "order": 91,
        "state": "complete",
        "round": 3,
        "player1": "Diamondback",
        "player2": "Kalma",
        "player1_id": 166697917,
        "player1_greenroom": 0,
        "player1_prereq": 269710545,
        "player2_id": 166697940,
        "player2_prereq": 269710546,
        "player2_greenroom": 0,
        "winner": "Diamondback",
        "loser": "Kalma",
        "updated_at": 1648322569,
        "underway": 0,
        "player1_lastFought": 1648314355,
        "player2_lastFought": 1648309433
    },
    "92": {
        "id": 269710568,
        "order": 92,
        "state": "complete",
        "round": 3,
        "player1": "Weta X",
        "player2": "Djem So",
        "player1_id": 166697965,
        "player1_greenroom": 0,
        "player1_prereq": 269710547,
        "player2_id": 166697924,
        "player2_prereq": 269710548,
        "player2_greenroom": 0,
        "winner": "Weta X",
        "loser": "Djem So",
        "updated_at": 1648327538,
        "underway": 0,
        "player1_lastFought": 1648314816,
        "player2_lastFought": 1648311819
    },
    "93": {
        "id": 269710569,
        "order": 93,
        "state": "complete",
        "round": 3,
        "player1": "Fully Defined",
        "player2": "Division",
        "player1_id": 166846904,
        "player1_greenroom": 0,
        "player1_prereq": 269710549,
        "player2_id": 166697930,
        "player2_prereq": 269710550,
        "player2_greenroom": 0,
        "winner": "Fully Defined",
        "loser": "Division",
        "updated_at": 1648322962,
        "underway": 0,
        "player1_lastFought": 1648315900,
        "player2_lastFought": 1648310589
    },
    "94": {
        "id": 269710570,
        "order": 94,
        "state": "complete",
        "round": 3,
        "player1": "Silk",
        "player2": "The Immortal 'Crixus'",
        "player1_id": 166697907,
        "player1_greenroom": 0,
        "player1_prereq": 269710551,
        "player2_id": 166697946,
        "player2_prereq": 269710552,
        "player2_greenroom": 0,
        "winner": "Silk",
        "loser": "The Immortal 'Crixus'",
        "updated_at": 1648324936,
        "underway": 0,
        "player1_lastFought": 1648314264,
        "player2_lastFought": 1648310487
    },
    "95": {
        "id": 269710571,
        "order": 95,
        "state": "complete",
        "round": 3,
        "player1": "Voxel",
        "player2": "Clyde",
        "player1_id": 166697908,
        "player1_greenroom": 0,
        "player1_prereq": 269710553,
        "player2_id": 166697938,
        "player2_prereq": 269710554,
        "player2_greenroom": 0,
        "winner": "Clyde",
        "loser": "Voxel",
        "updated_at": 1648327303,
        "underway": 0,
        "player1_lastFought": 1648315303,
        "player2_lastFought": 1648307161
    },
    "96": {
        "id": 269710572,
        "order": 96,
        "state": "complete",
        "round": 3,
        "player1": "Silent Spring",
        "player2": "Tothik",
        "player1_id": 166697905,
        "player1_greenroom": 0,
        "player1_prereq": 269710555,
        "player2_id": 166697923,
        "player2_prereq": 269710556,
        "player2_greenroom": 0,
        "winner": "Tothik",
        "loser": "Silent Spring",
        "updated_at": 1648320851,
        "underway": 0,
        "player1_lastFought": 1648316203,
        "player2_lastFought": 1648306686
    },
    "121": {
        "id": 269710573,
        "order": 121,
        "state": "complete",
        "round": 4,
        "player1": "Tiefschlag",
        "player2": "Sea Dragons Roar",
        "player1_id": 166697932,
        "player1_greenroom": 0,
        "player1_prereq": 269710557,
        "player2_id": 166697948,
        "player2_prereq": 269710558,
        "player2_greenroom": 0,
        "winner": "Sea Dragons Roar",
        "loser": "Tiefschlag",
        "updated_at": 1648327832,
        "underway": 0,
        "player1_lastFought": 1648321341,
        "player2_lastFought": 1648323651
    },
    "122": {
        "id": 269710574,
        "order": 122,
        "state": "complete",
        "round": 4,
        "player1": "Starchild",
        "player2": "Caldera",
        "player1_id": 166697910,
        "player1_greenroom": 0,
        "player1_prereq": 269710559,
        "player2_id": 166697911,
        "player2_prereq": 269710560,
        "player2_greenroom": 0,
        "winner": "Starchild",
        "loser": "Caldera",
        "updated_at": 1648329049,
        "underway": 0,
        "player1_lastFought": 1648325287,
        "player2_lastFought": 1648322334
    },
    "123": {
        "id": 269710575,
        "order": 123,
        "state": "complete",
        "round": 4,
        "player1": "Red Hawk",
        "player2": "Jack Move",
        "player1_id": 166697906,
        "player1_greenroom": 0,
        "player1_prereq": 269710561,
        "player2_id": 166697921,
        "player2_prereq": 269710562,
        "player2_greenroom": 0,
        "winner": "Jack Move",
        "loser": "Red Hawk",
        "updated_at": 1648326456,
        "underway": 0,
        "player1_lastFought": 1648321410,
        "player2_lastFought": 1648322018
    },
    "124": {
        "id": 269710576,
        "order": 124,
        "state": "complete",
        "round": 4,
        "player1": "Sepi01",
        "player2": "Stoneforge",
        "player1_id": 166697915,
        "player1_greenroom": 0,
        "player1_prereq": 269710563,
        "player2_id": 166697922,
        "player2_prereq": 269710564,
        "player2_greenroom": 0,
        "winner": "Stoneforge",
        "loser": "Sepi01",
        "updated_at": 1648330376,
        "underway": 0,
        "player1_lastFought": 1648323570,
        "player2_lastFought": 1648324556
    },
    "125": {
        "id": 269710577,
        "order": 125,
        "state": "complete",
        "round": 4,
        "player1": "Adrift",
        "player2": "Shreddit Bro",
        "player1_id": 166697916,
        "player1_greenroom": 0,
        "player1_prereq": 269710565,
        "player2_id": 166697904,
        "player2_prereq": 269710566,
        "player2_greenroom": 0,
        "winner": "Adrift",
        "loser": "Shreddit Bro",
        "updated_at": 1648332416,
        "underway": 0,
        "player1_lastFought": 1648324679,
        "player2_lastFought": 1648326605
    },
    "126": {
        "id": 269710578,
        "order": 126,
        "state": "complete",
        "round": 4,
        "player1": "Diamondback",
        "player2": "Weta X",
        "player1_id": 166697917,
        "player1_greenroom": 0,
        "player1_prereq": 269710567,
        "player2_id": 166697965,
        "player2_prereq": 269710568,
        "player2_greenroom": 0,
        "winner": "Weta X",
        "loser": "Diamondback",
        "updated_at": 1648335639,
        "underway": 0,
        "player1_lastFought": 1648322569,
        "player2_lastFought": 1648327538
    },
    "127": {
        "id": 269710579,
        "order": 127,
        "state": "complete",
        "round": 4,
        "player1": "Fully Defined",
        "player2": "Silk",
        "player1_id": 166846904,
        "player1_greenroom": 0,
        "player1_prereq": 269710569,
        "player2_id": 166697907,
        "player2_prereq": 269710570,
        "player2_greenroom": 0,
        "winner": "Silk",
        "loser": "Fully Defined",
        "updated_at": 1648329709,
        "underway": 0,
        "player1_lastFought": 1648322962,
        "player2_lastFought": 1648324936
    },
    "128": {
        "id": 269710580,
        "order": 128,
        "state": "complete",
        "round": 4,
        "player1": "Clyde",
        "player2": "Tothik",
        "player1_id": 166697938,
        "player1_greenroom": 0,
        "player1_prereq": 269710571,
        "player2_id": 166697923,
        "player2_prereq": 269710572,
        "player2_greenroom": 0,
        "winner": "Clyde",
        "loser": "Tothik",
        "updated_at": 1648333834,
        "underway": 0,
        "player1_lastFought": 1648327303,
        "player2_lastFought": 1648320851
    },
    "141": {
        "id": 269710581,
        "order": 141,
        "state": "complete",
        "round": 5,
        "player1": "Sea Dragons Roar",
        "player2": "Starchild",
        "player1_id": 166697948,
        "player1_greenroom": 0,
        "player1_prereq": 269710573,
        "player2_id": 166697910,
        "player2_prereq": 269710574,
        "player2_greenroom": 0,
        "winner": "Sea Dragons Roar",
        "loser": "Starchild",
        "updated_at": 1648334154,
        "underway": 0,
        "player1_lastFought": 1648327832,
        "player2_lastFought": 1648329049
    },
    "142": {
        "id": 269710582,
        "order": 142,
        "state": "complete",
        "round": 5,
        "player1": "Jack Move",
        "player2": "Stoneforge",
        "player1_id": 166697921,
        "player1_greenroom": 0,
        "player1_prereq": 269710575,
        "player2_id": 166697922,
        "player2_prereq": 269710576,
        "player2_greenroom": 0,
        "winner": "Stoneforge",
        "loser": "Jack Move",
        "updated_at": 1648337214,
        "underway": 0,
        "player1_lastFought": 1648326456,
        "player2_lastFought": 1648330376
    },
    "143": {
        "id": 269710583,
        "order": 143,
        "state": "complete",
        "round": 5,
        "player1": "Adrift",
        "player2": "Weta X",
        "player1_id": 166697916,
        "player1_greenroom": 0,
        "player1_prereq": 269710577,
        "player2_id": 166697965,
        "player2_prereq": 269710578,
        "player2_greenroom": 0,
        "winner": "Adrift",
        "loser": "Weta X",
        "updated_at": 1648336450,
        "underway": 0,
        "player1_lastFought": 1648332416,
        "player2_lastFought": 1648335639
    },
    "144": {
        "id": 269710584,
        "order": 144,
        "state": "complete",
        "round": 5,
        "player1": "Silk",
        "player2": "Clyde",
        "player1_id": 166697907,
        "player1_greenroom": 0,
        "player1_prereq": 269710579,
        "player2_id": 166697938,
        "player2_prereq": 269710580,
        "player2_greenroom": 0,
        "winner": "Silk",
        "loser": "Clyde",
        "updated_at": 1648338850,
        "underway": 0,
        "player1_lastFought": 1648329709,
        "player2_lastFought": 1648333834
    },
    "151": {
        "id": 269710585,
        "order": 151,
        "state": "complete",
        "round": 6,
        "player1": "Sea Dragons Roar",
        "player2": "Stoneforge",
        "player1_id": 166697948,
        "player1_greenroom": 0,
        "player1_prereq": 269710581,
        "player2_id": 166697922,
        "player2_prereq": 269710582,
        "player2_greenroom": 0,
        "winner": "Stoneforge",
        "loser": "Sea Dragons Roar",
        "updated_at": 1648339599,
        "underway": 0,
        "player1_lastFought": 1648334154,
        "player2_lastFought": 1648337214
    },
    "152": {
        "id": 269710586,
        "order": 152,
        "state": "complete",
        "round": 6,
        "player1": "Adrift",
        "player2": "Silk",
        "player1_id": 166697916,
        "player1_greenroom": 0,
        "player1_prereq": 269710583,
        "player2_id": 166697907,
        "player2_prereq": 269710584,
        "player2_greenroom": 0,
        "winner": "Silk",
        "loser": "Adrift",
        "updated_at": 1648341923,
        "underway": 0,
        "player1_lastFought": 1648336450,
        "player2_lastFought": 1648338850
    },
    "156": {
        "id": 269710587,
        "order": 156,
        "state": "complete",
        "round": 7,
        "player1": "Stoneforge",
        "player2": "Silk",
        "player1_id": 166697922,
        "player1_greenroom": 0,
        "player1_prereq": 269710585,
        "player2_id": 166697907,
        "player2_prereq": 269710586,
        "player2_greenroom": 0,
        "winner": "Stoneforge",
        "loser": "Silk",
        "updated_at": 1648346798,
        "underway": 0,
        "player1_lastFought": 1648339599,
        "player2_lastFought": 1648341923
    },
    "64": {
        "id": 269710588,
        "order": 64,
        "state": "complete",
        "round": -1,
        "player1": "Da Dum Tsss",
        "player2": "Michael the Robot",
        "player1_id": 166697944,
        "player1_greenroom": 0,
        "player1_prereq": 269710556,
        "player2_id": 166697979,
        "player2_prereq": 269710509,
        "player2_greenroom": 0,
        "winner": "Michael the Robot",
        "loser": "Da Dum Tsss",
        "updated_at": 1648315389,
        "underway": 0,
        "player1_lastFought": 1648306686,
        "player2_lastFought": 1648312604
    },
    "63": {
        "id": 269710589,
        "order": 63,
        "state": "complete",
        "round": -1,
        "player1": "Taurine",
        "player2": "Copy & Paste Mach 2",
        "player1_id": 166697927,
        "player1_greenroom": 0,
        "player1_prereq": 269710554,
        "player2_id": 166697949,
        "player2_prereq": 269710510,
        "player2_greenroom": 0,
        "winner": "Taurine",
        "loser": "Copy & Paste Mach 2",
        "updated_at": 1648311579,
        "underway": 0,
        "player1_lastFought": 1648307161,
        "player2_lastFought": 1648306019
    },
    "62": {
        "id": 269710590,
        "order": 62,
        "state": "complete",
        "round": -1,
        "player1": "Spartan X",
        "player2": "PinevictuX",
        "player1_id": 166697920,
        "player1_greenroom": 0,
        "player1_prereq": 269710552,
        "player2_id": 166697958,
        "player2_prereq": 269710511,
        "player2_greenroom": 0,
        "winner": "Spartan X",
        "loser": "PinevictuX",
        "updated_at": 1648316730,
        "underway": 0,
        "player1_lastFought": 1648310487,
        "player2_lastFought": 1648310277
    },
    "61": {
        "id": 269710591,
        "order": 61,
        "state": "complete",
        "round": -1,
        "player1": "Professor Hex",
        "player2": "Not A Hornet",
        "player1_id": 166697935,
        "player1_greenroom": 0,
        "player1_prereq": 269710550,
        "player2_id": 166697957,
        "player2_prereq": 269710512,
        "player2_greenroom": 0,
        "winner": "Not A Hornet",
        "loser": "Professor Hex",
        "updated_at": 1648315999,
        "underway": 0,
        "player1_lastFought": 1648310589,
        "player2_lastFought": 1648306473
    },
    "60": {
        "id": 269710592,
        "order": 60,
        "state": "complete",
        "round": -1,
        "player1": "Wormhole",
        "player2": "Insomnia",
        "player1_id": 166697942,
        "player1_greenroom": 0,
        "player1_prereq": 269710548,
        "player2_id": 166697969,
        "player2_prereq": 269710513,
        "player2_greenroom": 0,
        "winner": "Wormhole",
        "loser": "Insomnia",
        "updated_at": 1648315812,
        "underway": 0,
        "player1_lastFought": 1648311819,
        "player2_lastFought": 1648306075
    },
    "59": {
        "id": 269710593,
        "order": 59,
        "state": "complete",
        "round": -1,
        "player1": "ZZ Bot",
        "player2": "Indecisive Mess",
        "player1_id": 166697926,
        "player1_greenroom": 0,
        "player1_prereq": 269710546,
        "player2_id": 166697976,
        "player2_prereq": 269710514,
        "player2_greenroom": 0,
        "winner": "ZZ Bot",
        "loser": "Indecisive Mess",
        "updated_at": 1648318839,
        "underway": 0,
        "player1_lastFought": 1648309433,
        "player2_lastFought": 1648305719
    },
    "58": {
        "id": 269710594,
        "order": 58,
        "state": "complete",
        "round": -1,
        "player1": "The Shrew",
        "player2": "Brent the Brick",
        "player1_id": 166697947,
        "player1_greenroom": 0,
        "player1_prereq": 269710544,
        "player2_id": 166697959,
        "player2_prereq": 269710515,
        "player2_greenroom": 0,
        "winner": "Brent the Brick",
        "loser": "The Shrew",
        "updated_at": 1648315305,
        "underway": 0,
        "player1_lastFought": 1648310736,
        "player2_lastFought": 1648307144
    },
    "57": {
        "id": 269710595,
        "order": 57,
        "state": "complete",
        "round": -1,
        "player1": "Fallout",
        "player2": "Hot Pok\u00e9",
        "player1_id": 166697931,
        "player1_greenroom": 0,
        "player1_prereq": 269710542,
        "player2_id": 166697953,
        "player2_prereq": 269710516,
        "player2_greenroom": 0,
        "winner": "Fallout",
        "loser": "Hot Pok\u00e9",
        "updated_at": 1648316297,
        "underway": 0,
        "player1_lastFought": 1648312477,
        "player2_lastFought": 1648308302
    },
    "56": {
        "id": 269710596,
        "order": 56,
        "state": "complete",
        "round": -1,
        "player1": "Pensive Prosciutto",
        "player2": "Doctor Frankenpine",
        "player1_id": 166697943,
        "player1_greenroom": 0,
        "player1_prereq": 269710540,
        "player2_id": 166697967,
        "player2_prereq": 269710517,
        "player2_greenroom": 0,
        "winner": "Pensive Prosciutto",
        "loser": "Doctor Frankenpine",
        "updated_at": 1648316295,
        "underway": 0,
        "player1_lastFought": 1648311601,
        "player2_lastFought": 1648308077
    },
    "55": {
        "id": 269710597,
        "order": 55,
        "state": "complete",
        "round": -1,
        "player1": "ER Stingray",
        "player2": "electric sheep",
        "player1_id": 166697937,
        "player1_greenroom": 0,
        "player1_prereq": 269710538,
        "player2_id": 166697981,
        "player2_prereq": 269710518,
        "player2_greenroom": 0,
        "winner": "ER Stingray",
        "loser": "electric sheep",
        "updated_at": 1648316311,
        "underway": 0,
        "player1_lastFought": 1648309950,
        "player2_lastFought": 1648310775
    },
    "54": {
        "id": 269710598,
        "order": 54,
        "state": "complete",
        "round": -1,
        "player1": "Ratfish",
        "player2": "Voltage",
        "player1_id": 166697945,
        "player1_greenroom": 0,
        "player1_prereq": 269710536,
        "player2_id": 166697972,
        "player2_prereq": 269710519,
        "player2_greenroom": 0,
        "winner": "Voltage",
        "loser": "Ratfish",
        "updated_at": 1648313745,
        "underway": 0,
        "player1_lastFought": 1648308837,
        "player2_lastFought": 1648310663
    },
    "53": {
        "id": 269710599,
        "order": 53,
        "state": "complete",
        "round": -1,
        "player1": "Razor Storm",
        "player2": "Wreckfest",
        "player1_id": 166697929,
        "player1_greenroom": 0,
        "player1_prereq": 269710534,
        "player2_id": 166697955,
        "player2_prereq": 269710520,
        "player2_greenroom": 0,
        "winner": "Wreckfest",
        "loser": "Razor Storm",
        "updated_at": 1648311647,
        "underway": 0,
        "player1_lastFought": 1648308631,
        "player2_lastFought": 1648308041
    },
    "52": {
        "id": 269710600,
        "order": 52,
        "state": "complete",
        "round": -1,
        "player1": "PGF",
        "player2": "Katrina",
        "player1_id": 166697941,
        "player1_greenroom": 0,
        "player1_prereq": 269710532,
        "player2_id": 166697968,
        "player2_prereq": 269710521,
        "player2_greenroom": 0,
        "winner": "PGF",
        "loser": "Katrina",
        "updated_at": 1648315691,
        "underway": 0,
        "player1_lastFought": 1648310033,
        "player2_lastFought": 1648309547
    },
    "51": {
        "id": 269710601,
        "order": 51,
        "state": "complete",
        "round": -1,
        "player1": "Nitro Hornet",
        "player2": "The Chort",
        "player1_id": 166697956,
        "player1_greenroom": 0,
        "player1_prereq": 269710530,
        "player2_id": 166697980,
        "player2_prereq": 269710522,
        "player2_greenroom": 0,
        "winner": "The Chort",
        "loser": "Nitro Hornet",
        "updated_at": 1648318617,
        "underway": 0,
        "player1_lastFought": 1648308696,
        "player2_lastFought": 1648307111
    },
    "50": {
        "id": 269710602,
        "order": 50,
        "state": "complete",
        "round": -1,
        "player1": "Jet Lag",
        "player2": "Jeyla",
        "player1_id": 166697918,
        "player1_greenroom": 0,
        "player1_prereq": 269710528,
        "player2_id": 166697971,
        "player2_prereq": 269710523,
        "player2_greenroom": 0,
        "winner": "Jet Lag",
        "loser": "Jeyla",
        "updated_at": 1648321813,
        "underway": 0,
        "player1_lastFought": 1648307517,
        "player2_lastFought": 1648306149
    },
    "49": {
        "id": 269710603,
        "order": 49,
        "state": "complete",
        "round": -1,
        "player1": "Drum Go Dum",
        "player2": "Hurt Caboose",
        "player1_id": 166697933,
        "player1_greenroom": 0,
        "player1_prereq": 269710526,
        "player2_id": 166697954,
        "player2_prereq": 269710524,
        "player2_greenroom": 0,
        "winner": "Hurt Caboose",
        "loser": "Drum Go Dum",
        "updated_at": 1648315458,
        "underway": 0,
        "player1_lastFought": 1648307120,
        "player2_lastFought": 1648311070
    },
    "80": {
        "id": 269710604,
        "order": 80,
        "state": "complete",
        "round": -2,
        "player1": "Narcissist",
        "player2": "Michael the Robot",
        "player1_id": 166697975,
        "player1_greenroom": 0,
        "player1_prereq": 269710555,
        "player2_id": 166697979,
        "player2_prereq": 269710588,
        "player2_greenroom": 0,
        "winner": "Narcissist",
        "loser": "Michael the Robot",
        "updated_at": 1648320467,
        "underway": 0,
        "player1_lastFought": 1648316203,
        "player2_lastFought": 1648315389
    },
    "79": {
        "id": 269710605,
        "order": 79,
        "state": "complete",
        "round": -2,
        "player1": "Harvester",
        "player2": "Taurine",
        "player1_id": 166697961,
        "player1_greenroom": 0,
        "player1_prereq": 269710553,
        "player2_id": 166697927,
        "player2_prereq": 269710589,
        "player2_greenroom": 0,
        "winner": "Taurine",
        "loser": "Harvester",
        "updated_at": 1648318412,
        "underway": 0,
        "player1_lastFought": 1648315303,
        "player2_lastFought": 1648311579
    },
    "78": {
        "id": 269710606,
        "order": 78,
        "state": "complete",
        "round": -2,
        "player1": "Phantom III",
        "player2": "Spartan X",
        "player1_id": 166697951,
        "player1_greenroom": 0,
        "player1_prereq": 269710551,
        "player2_id": 166697920,
        "player2_prereq": 269710590,
        "player2_greenroom": 0,
        "winner": "Spartan X",
        "loser": "Phantom III",
        "updated_at": 1648322236,
        "underway": 0,
        "player1_lastFought": 1648314264,
        "player2_lastFought": 1648316730
    },
    "77": {
        "id": 269710607,
        "order": 77,
        "state": "complete",
        "round": -2,
        "player1": "Tygre Claw",
        "player2": "Not A Hornet",
        "player1_id": 166697963,
        "player1_greenroom": 0,
        "player1_prereq": 269710549,
        "player2_id": 166697957,
        "player2_prereq": 269710591,
        "player2_greenroom": 0,
        "winner": "Tygre Claw",
        "loser": "Not A Hornet",
        "updated_at": 1648319700,
        "underway": 0,
        "player1_lastFought": 1648315900,
        "player2_lastFought": 1648315999
    },
    "76": {
        "id": 269710608,
        "order": 76,
        "state": "complete",
        "round": -2,
        "player1": "Blackbird",
        "player2": "Wormhole",
        "player1_id": 166697912,
        "player1_greenroom": 0,
        "player1_prereq": 269710547,
        "player2_id": 166697942,
        "player2_prereq": 269710592,
        "player2_greenroom": 0,
        "winner": "Blackbird",
        "loser": "Wormhole",
        "updated_at": 1648320130,
        "underway": 0,
        "player1_lastFought": 1648314816,
        "player2_lastFought": 1648315812
    },
    "75": {
        "id": 269710609,
        "order": 75,
        "state": "complete",
        "round": -2,
        "player1": "Titanium Knight",
        "player2": "ZZ Bot",
        "player1_id": 166697960,
        "player1_greenroom": 0,
        "player1_prereq": 269710545,
        "player2_id": 166697926,
        "player2_prereq": 269710593,
        "player2_greenroom": 0,
        "winner": "Titanium Knight",
        "loser": "ZZ Bot",
        "updated_at": 1648324462,
        "underway": 0,
        "player1_lastFought": 1648314355,
        "player2_lastFought": 1648318839
    },
    "74": {
        "id": 269710610,
        "order": 74,
        "state": "complete",
        "round": -2,
        "player1": "Be Careful What You Wish For",
        "player2": "Brent the Brick",
        "player1_id": 166697950,
        "player1_greenroom": 0,
        "player1_prereq": 269710543,
        "player2_id": 166697959,
        "player2_prereq": 269710594,
        "player2_greenroom": 0,
        "winner": "Be Careful What You Wish For",
        "loser": "Brent the Brick",
        "updated_at": 1648323634,
        "underway": 0,
        "player1_lastFought": 1648316841,
        "player2_lastFought": 1648315305
    },
    "73": {
        "id": 269710611,
        "order": 73,
        "state": "complete",
        "round": -2,
        "player1": "V.A.C.0.O.M",
        "player2": "Fallout",
        "player1_id": 166697964,
        "player1_greenroom": 0,
        "player1_prereq": 269710541,
        "player2_id": 166697931,
        "player2_prereq": 269710595,
        "player2_greenroom": 0,
        "winner": "Fallout",
        "loser": "V.A.C.0.O.M",
        "updated_at": 1648319893,
        "underway": 0,
        "player1_lastFought": 1648313538,
        "player2_lastFought": 1648316297
    },
    "72": {
        "id": 269710612,
        "order": 72,
        "state": "complete",
        "round": -2,
        "player1": "Chubby Unicorn",
        "player2": "Pensive Prosciutto",
        "player1_id": 166697977,
        "player1_greenroom": 0,
        "player1_prereq": 269710539,
        "player2_id": 166697943,
        "player2_prereq": 269710596,
        "player2_greenroom": 0,
        "winner": "Pensive Prosciutto",
        "loser": "Chubby Unicorn",
        "updated_at": 1648318731,
        "underway": 0,
        "player1_lastFought": 1648314615,
        "player2_lastFought": 1648316295
    },
    "71": {
        "id": 269710613,
        "order": 71,
        "state": "complete",
        "round": -2,
        "player1": "Jenson",
        "player2": "ER Stingray",
        "player1_id": 166697970,
        "player1_greenroom": 0,
        "player1_prereq": 269710537,
        "player2_id": 166697937,
        "player2_prereq": 269710597,
        "player2_greenroom": 0,
        "winner": "ER Stingray",
        "loser": "Jenson",
        "updated_at": 1648319806,
        "underway": 0,
        "player1_lastFought": 1648313373,
        "player2_lastFought": 1648316311
    },
    "70": {
        "id": 269710614,
        "order": 70,
        "state": "complete",
        "round": -2,
        "player1": "Black Adder",
        "player2": "Voltage",
        "player1_id": 166697914,
        "player1_greenroom": 0,
        "player1_prereq": 269710535,
        "player2_id": 166697972,
        "player2_prereq": 269710598,
        "player2_greenroom": 0,
        "winner": "Voltage",
        "loser": "Black Adder",
        "updated_at": 1648318073,
        "underway": 0,
        "player1_lastFought": 1648313439,
        "player2_lastFought": 1648313745
    },
    "69": {
        "id": 269710615,
        "order": 69,
        "state": "complete",
        "round": -2,
        "player1": "Arr See Saw",
        "player2": "Wreckfest",
        "player1_id": 166697962,
        "player1_greenroom": 0,
        "player1_prereq": 269710533,
        "player2_id": 166697955,
        "player2_prereq": 269710599,
        "player2_greenroom": 0,
        "winner": "Wreckfest",
        "loser": "Arr See Saw",
        "updated_at": 1648318659,
        "underway": 0,
        "player1_lastFought": 1648313616,
        "player2_lastFought": 1648311647
    },
    "68": {
        "id": 269710616,
        "order": 68,
        "state": "complete",
        "round": -2,
        "player1": "DeNiteMare",
        "player2": "PGF",
        "player1_id": 166697974,
        "player1_greenroom": 0,
        "player1_prereq": 269710531,
        "player2_id": 166697941,
        "player2_prereq": 269710600,
        "player2_greenroom": 0,
        "winner": "DeNiteMare",
        "loser": "PGF",
        "updated_at": 1648322529,
        "underway": 0,
        "player1_lastFought": 1648316972,
        "player2_lastFought": 1648315691
    },
    "67": {
        "id": 269710617,
        "order": 67,
        "state": "complete",
        "round": -2,
        "player1": "Saber",
        "player2": "The Chort",
        "player1_id": 166697973,
        "player1_greenroom": 0,
        "player1_prereq": 269710529,
        "player2_id": 166697980,
        "player2_prereq": 269710601,
        "player2_greenroom": 0,
        "winner": "The Chort",
        "loser": "Saber",
        "updated_at": 1648321024,
        "underway": 0,
        "player1_lastFought": 1648315178,
        "player2_lastFought": 1648318617
    },
    "66": {
        "id": 269710618,
        "order": 66,
        "state": "complete",
        "round": -2,
        "player1": "Amen Break",
        "player2": "Jet Lag",
        "player1_id": 166697982,
        "player1_greenroom": 0,
        "player1_prereq": 269710527,
        "player2_id": 166697918,
        "player2_prereq": 269710602,
        "player2_greenroom": 0,
        "winner": "Jet Lag",
        "loser": "Amen Break",
        "updated_at": 1648321838,
        "underway": 0,
        "player1_lastFought": 1648312635,
        "player2_lastFought": 1648321813
    },
    "65": {
        "id": 269710619,
        "order": 65,
        "state": "complete",
        "round": -2,
        "player1": "Eruption",
        "player2": "Hurt Caboose",
        "player1_id": 166697903,
        "player1_greenroom": 0,
        "player1_prereq": 269710525,
        "player2_id": 166697954,
        "player2_prereq": 269710603,
        "player2_greenroom": 0,
        "winner": "Hurt Caboose",
        "loser": "Eruption",
        "updated_at": 1648321186,
        "underway": 0,
        "player1_lastFought": 1648313041,
        "player2_lastFought": 1648315458
    },
    "104": {
        "id": 269710620,
        "order": 104,
        "state": "complete",
        "round": -3,
        "player1": "Yes Chef Classic",
        "player2": "Narcissist",
        "player1_id": 166697913,
        "player1_greenroom": 0,
        "player1_prereq": 269710564,
        "player2_id": 166697975,
        "player2_prereq": 269710604,
        "player2_greenroom": 0,
        "winner": "Narcissist",
        "loser": "Yes Chef Classic",
        "updated_at": 1648327636,
        "underway": 0,
        "player1_lastFought": 1648324556,
        "player2_lastFought": 1648320467
    },
    "103": {
        "id": 269710621,
        "order": 103,
        "state": "complete",
        "round": -3,
        "player1": "LuxRay Mega X",
        "player2": "Taurine",
        "player1_id": 166697928,
        "player1_greenroom": 0,
        "player1_prereq": 269710563,
        "player2_id": 166697927,
        "player2_prereq": 269710605,
        "player2_greenroom": 0,
        "winner": "Taurine",
        "loser": "LuxRay Mega X",
        "updated_at": 1648327446,
        "underway": 0,
        "player1_lastFought": 1648323570,
        "player2_lastFought": 1648318412
    },
    "102": {
        "id": 269710622,
        "order": 102,
        "state": "complete",
        "round": -3,
        "player1": "Twisty",
        "player2": "Spartan X",
        "player1_id": 166697952,
        "player1_greenroom": 0,
        "player1_prereq": 269710562,
        "player2_id": 166697920,
        "player2_prereq": 269710606,
        "player2_greenroom": 0,
        "winner": "Spartan X",
        "loser": "Twisty",
        "updated_at": 1648332112,
        "underway": 0,
        "player1_lastFought": 1648322018,
        "player2_lastFought": 1648322236
    },
    "101": {
        "id": 269710623,
        "order": 101,
        "state": "complete",
        "round": -3,
        "player1": "Apex",
        "player2": "Tygre Claw",
        "player1_id": 166697936,
        "player1_greenroom": 0,
        "player1_prereq": 269710561,
        "player2_id": 166697963,
        "player2_prereq": 269710607,
        "player2_greenroom": 0,
        "winner": "Apex",
        "loser": "Tygre Claw",
        "updated_at": 1648326116,
        "underway": 0,
        "player1_lastFought": 1648321410,
        "player2_lastFought": 1648319700
    },
    "100": {
        "id": 269710624,
        "order": 100,
        "state": "complete",
        "round": -3,
        "player1": "Wicked Wedge",
        "player2": "Blackbird",
        "player1_id": 166697925,
        "player1_greenroom": 0,
        "player1_prereq": 269710560,
        "player2_id": 166697912,
        "player2_prereq": 269710608,
        "player2_greenroom": 0,
        "winner": "Blackbird",
        "loser": "Wicked Wedge",
        "updated_at": 1648326918,
        "underway": 0,
        "player1_lastFought": 1648322334,
        "player2_lastFought": 1648320130
    },
    "99": {
        "id": 269710625,
        "order": 99,
        "state": "complete",
        "round": -3,
        "player1": "Ti",
        "player2": "Titanium Knight",
        "player1_id": 166697939,
        "player1_greenroom": 0,
        "player1_prereq": 269710559,
        "player2_id": 166697960,
        "player2_prereq": 269710609,
        "player2_greenroom": 0,
        "winner": "Ti",
        "loser": "Titanium Knight",
        "updated_at": 1648328961,
        "underway": 0,
        "player1_lastFought": 1648325287,
        "player2_lastFought": 1648324462
    },
    "98": {
        "id": 269710626,
        "order": 98,
        "state": "complete",
        "round": -3,
        "player1": "Jack Rabbit",
        "player2": "Be Careful What You Wish For",
        "player1_id": 166697909,
        "player1_greenroom": 0,
        "player1_prereq": 269710558,
        "player2_id": 166697950,
        "player2_prereq": 269710610,
        "player2_greenroom": 0,
        "winner": "Jack Rabbit",
        "loser": "Be Careful What You Wish For",
        "updated_at": 1648329823,
        "underway": 0,
        "player1_lastFought": 1648323651,
        "player2_lastFought": 1648323634
    },
    "97": {
        "id": 269710627,
        "order": 97,
        "state": "complete",
        "round": -3,
        "player1": "Rachet",
        "player2": "Fallout",
        "player1_id": 166697966,
        "player1_greenroom": 0,
        "player1_prereq": 269710557,
        "player2_id": 166697931,
        "player2_prereq": 269710611,
        "player2_greenroom": 0,
        "winner": "Rachet",
        "loser": "Fallout",
        "updated_at": 1648325593,
        "underway": 0,
        "player1_lastFought": 1648321341,
        "player2_lastFought": 1648319893
    },
    "112": {
        "id": 269710628,
        "order": 112,
        "state": "complete",
        "round": -3,
        "player1": "Silent Spring",
        "player2": "Pensive Prosciutto",
        "player1_id": 166697905,
        "player1_greenroom": 0,
        "player1_prereq": 269710572,
        "player2_id": 166697943,
        "player2_prereq": 269710612,
        "player2_greenroom": 0,
        "winner": "Silent Spring",
        "loser": "Pensive Prosciutto",
        "updated_at": 1648323257,
        "underway": 0,
        "player1_lastFought": 1648320851,
        "player2_lastFought": 1648318731
    },
    "111": {
        "id": 269710629,
        "order": 111,
        "state": "complete",
        "round": -3,
        "player1": "Voxel",
        "player2": "ER Stingray",
        "player1_id": 166697908,
        "player1_greenroom": 0,
        "player1_prereq": 269710571,
        "player2_id": 166697937,
        "player2_prereq": 269710613,
        "player2_greenroom": 0,
        "winner": "ER Stingray",
        "loser": "Voxel",
        "updated_at": 1648331575,
        "underway": 0,
        "player1_lastFought": 1648327303,
        "player2_lastFought": 1648319806
    },
    "110": {
        "id": 269710630,
        "order": 110,
        "state": "complete",
        "round": -3,
        "player1": "The Immortal 'Crixus'",
        "player2": "Voltage",
        "player1_id": 166697946,
        "player1_greenroom": 0,
        "player1_prereq": 269710570,
        "player2_id": 166697972,
        "player2_prereq": 269710614,
        "player2_greenroom": 0,
        "winner": "Voltage",
        "loser": "The Immortal 'Crixus'",
        "updated_at": 1648331007,
        "underway": 0,
        "player1_lastFought": 1648324936,
        "player2_lastFought": 1648318073
    },
    "109": {
        "id": 269710631,
        "order": 109,
        "state": "complete",
        "round": -3,
        "player1": "Division",
        "player2": "Wreckfest",
        "player1_id": 166697930,
        "player1_greenroom": 0,
        "player1_prereq": 269710569,
        "player2_id": 166697955,
        "player2_prereq": 269710615,
        "player2_greenroom": 0,
        "winner": "Wreckfest",
        "loser": "Division",
        "updated_at": 1648326258,
        "underway": 0,
        "player1_lastFought": 1648322962,
        "player2_lastFought": 1648318659
    },
    "108": {
        "id": 269710632,
        "order": 108,
        "state": "complete",
        "round": -3,
        "player1": "Djem So",
        "player2": "DeNiteMare",
        "player1_id": 166697924,
        "player1_greenroom": 0,
        "player1_prereq": 269710568,
        "player2_id": 166697974,
        "player2_prereq": 269710616,
        "player2_greenroom": 0,
        "winner": "Djem So",
        "loser": "DeNiteMare",
        "updated_at": 1648332432,
        "underway": 0,
        "player1_lastFought": 1648327538,
        "player2_lastFought": 1648322529
    },
    "107": {
        "id": 269710633,
        "order": 107,
        "state": "complete",
        "round": -3,
        "player1": "Kalma",
        "player2": "The Chort",
        "player1_id": 166697940,
        "player1_greenroom": 0,
        "player1_prereq": 269710567,
        "player2_id": 166697980,
        "player2_prereq": 269710617,
        "player2_greenroom": 0,
        "winner": "Kalma",
        "loser": "The Chort",
        "updated_at": 1648324819,
        "underway": 0,
        "player1_lastFought": 1648322569,
        "player2_lastFought": 1648321024
    },
    "106": {
        "id": 269710634,
        "order": 106,
        "state": "complete",
        "round": -3,
        "player1": "War? Hard!",
        "player2": "Jet Lag",
        "player1_id": 166697919,
        "player1_greenroom": 0,
        "player1_prereq": 269710566,
        "player2_id": 166697918,
        "player2_prereq": 269710618,
        "player2_greenroom": 0,
        "winner": "Jet Lag",
        "loser": "War? Hard!",
        "updated_at": 1648333238,
        "underway": 0,
        "player1_lastFought": 1648326605,
        "player2_lastFought": 1648321838
    },
    "105": {
        "id": 269710635,
        "order": 105,
        "state": "complete",
        "round": -3,
        "player1": "Voxel v.1",
        "player2": "Hurt Caboose",
        "player1_id": 166697934,
        "player1_greenroom": 0,
        "player1_prereq": 269710565,
        "player2_id": 166697954,
        "player2_prereq": 269710619,
        "player2_greenroom": 0,
        "winner": "Hurt Caboose",
        "loser": "Voxel v.1",
        "updated_at": 1648330018,
        "underway": 0,
        "player1_lastFought": 1648324679,
        "player2_lastFought": 1648321186
    },
    "116": {
        "id": 269710636,
        "order": 116,
        "state": "complete",
        "round": -4,
        "player1": "Narcissist",
        "player2": "Taurine",
        "player1_id": 166697975,
        "player1_greenroom": 0,
        "player1_prereq": 269710620,
        "player2_id": 166697927,
        "player2_prereq": 269710621,
        "player2_greenroom": 0,
        "winner": "Narcissist",
        "loser": "Taurine",
        "updated_at": 1648331285,
        "underway": 0,
        "player1_lastFought": 1648327636,
        "player2_lastFought": 1648327446
    },
    "115": {
        "id": 269710637,
        "order": 115,
        "state": "complete",
        "round": -4,
        "player1": "Spartan X",
        "player2": "Apex",
        "player1_id": 166697920,
        "player1_greenroom": 0,
        "player1_prereq": 269710622,
        "player2_id": 166697936,
        "player2_prereq": 269710623,
        "player2_greenroom": 0,
        "winner": "Spartan X",
        "loser": "Apex",
        "updated_at": 1648332890,
        "underway": 0,
        "player1_lastFought": 1648332112,
        "player2_lastFought": 1648326116
    },
    "114": {
        "id": 269710638,
        "order": 114,
        "state": "complete",
        "round": -4,
        "player1": "Blackbird",
        "player2": "Ti",
        "player1_id": 166697912,
        "player1_greenroom": 0,
        "player1_prereq": 269710624,
        "player2_id": 166697939,
        "player2_prereq": 269710625,
        "player2_greenroom": 0,
        "winner": "Blackbird",
        "loser": "Ti",
        "updated_at": 1648331469,
        "underway": 0,
        "player1_lastFought": 1648326918,
        "player2_lastFought": 1648328961
    },
    "113": {
        "id": 269710639,
        "order": 113,
        "state": "complete",
        "round": -4,
        "player1": "Jack Rabbit",
        "player2": "Rachet",
        "player1_id": 166697909,
        "player1_greenroom": 0,
        "player1_prereq": 269710626,
        "player2_id": 166697966,
        "player2_prereq": 269710627,
        "player2_greenroom": 0,
        "winner": "Jack Rabbit",
        "loser": "Rachet",
        "updated_at": 1648333498,
        "underway": 0,
        "player1_lastFought": 1648329823,
        "player2_lastFought": 1648325593
    },
    "120": {
        "id": 269710640,
        "order": 120,
        "state": "complete",
        "round": -4,
        "player1": "Silent Spring",
        "player2": "ER Stingray",
        "player1_id": 166697905,
        "player1_greenroom": 0,
        "player1_prereq": 269710628,
        "player2_id": 166697937,
        "player2_prereq": 269710629,
        "player2_greenroom": 0,
        "winner": "Silent Spring",
        "loser": "ER Stingray",
        "updated_at": 1648335392,
        "underway": 0,
        "player1_lastFought": 1648323257,
        "player2_lastFought": 1648331575
    },
    "119": {
        "id": 269710641,
        "order": 119,
        "state": "complete",
        "round": -4,
        "player1": "Voltage",
        "player2": "Wreckfest",
        "player1_id": 166697972,
        "player1_greenroom": 0,
        "player1_prereq": 269710630,
        "player2_id": 166697955,
        "player2_prereq": 269710631,
        "player2_greenroom": 0,
        "winner": "Wreckfest",
        "loser": "Voltage",
        "updated_at": 1648334588,
        "underway": 0,
        "player1_lastFought": 1648331007,
        "player2_lastFought": 1648326258
    },
    "118": {
        "id": 269710642,
        "order": 118,
        "state": "complete",
        "round": -4,
        "player1": "Djem So",
        "player2": "Kalma",
        "player1_id": 166697924,
        "player1_greenroom": 0,
        "player1_prereq": 269710632,
        "player2_id": 166697940,
        "player2_prereq": 269710633,
        "player2_greenroom": 0,
        "winner": "Djem So",
        "loser": "Kalma",
        "updated_at": 1648337503,
        "underway": 0,
        "player1_lastFought": 1648332432,
        "player2_lastFought": 1648324819
    },
    "117": {
        "id": 269710643,
        "order": 117,
        "state": "complete",
        "round": -4,
        "player1": "Jet Lag",
        "player2": "Hurt Caboose",
        "player1_id": 166697918,
        "player1_greenroom": 0,
        "player1_prereq": 269710634,
        "player2_id": 166697954,
        "player2_prereq": 269710635,
        "player2_greenroom": 0,
        "winner": "Jet Lag",
        "loser": "Hurt Caboose",
        "updated_at": 1648335694,
        "underway": 0,
        "player1_lastFought": 1648333238,
        "player2_lastFought": 1648330018
    },
    "133": {
        "id": 269710644,
        "order": 133,
        "state": "complete",
        "round": -5,
        "player1": "Shreddit Bro",
        "player2": "Narcissist",
        "player1_id": 166697904,
        "player1_greenroom": 0,
        "player1_prereq": 269710577,
        "player2_id": 166697975,
        "player2_prereq": 269710636,
        "player2_greenroom": 0,
        "winner": "Narcissist",
        "loser": "Shreddit Bro",
        "updated_at": 1648336323,
        "underway": 0,
        "player1_lastFought": 1648332416,
        "player2_lastFought": 1648331285
    },
    "134": {
        "id": 269710645,
        "order": 134,
        "state": "complete",
        "round": -5,
        "player1": "Diamondback",
        "player2": "Spartan X",
        "player1_id": 166697917,
        "player1_greenroom": 0,
        "player1_prereq": 269710578,
        "player2_id": 166697920,
        "player2_prereq": 269710637,
        "player2_greenroom": 0,
        "winner": "Spartan X",
        "loser": "Diamondback",
        "updated_at": 1648335653,
        "underway": 0,
        "player1_lastFought": 1648335639,
        "player2_lastFought": 1648332890
    },
    "135": {
        "id": 269710646,
        "order": 135,
        "state": "complete",
        "round": -5,
        "player1": "Fully Defined",
        "player2": "Blackbird",
        "player1_id": 166846904,
        "player1_greenroom": 0,
        "player1_prereq": 269710579,
        "player2_id": 166697912,
        "player2_prereq": 269710638,
        "player2_greenroom": 0,
        "winner": "Blackbird",
        "loser": "Fully Defined",
        "updated_at": 1648334080,
        "underway": 0,
        "player1_lastFought": 1648329709,
        "player2_lastFought": 1648331469
    },
    "136": {
        "id": 269710647,
        "order": 136,
        "state": "complete",
        "round": -5,
        "player1": "Tothik",
        "player2": "Jack Rabbit",
        "player1_id": 166697923,
        "player1_greenroom": 0,
        "player1_prereq": 269710580,
        "player2_id": 166697909,
        "player2_prereq": 269710639,
        "player2_greenroom": 0,
        "winner": "Tothik",
        "loser": "Jack Rabbit",
        "updated_at": 1648340437,
        "underway": 0,
        "player1_lastFought": 1648333834,
        "player2_lastFought": 1648333498
    },
    "129": {
        "id": 269710648,
        "order": 129,
        "state": "complete",
        "round": -5,
        "player1": "Tiefschlag",
        "player2": "Silent Spring",
        "player1_id": 166697932,
        "player1_greenroom": 0,
        "player1_prereq": 269710573,
        "player2_id": 166697905,
        "player2_prereq": 269710640,
        "player2_greenroom": 0,
        "winner": "Silent Spring",
        "loser": "Tiefschlag",
        "updated_at": 1648338220,
        "underway": 0,
        "player1_lastFought": 1648327832,
        "player2_lastFought": 1648335392
    },
    "130": {
        "id": 269710649,
        "order": 130,
        "state": "complete",
        "round": -5,
        "player1": "Caldera",
        "player2": "Wreckfest",
        "player1_id": 166697911,
        "player1_greenroom": 0,
        "player1_prereq": 269710574,
        "player2_id": 166697955,
        "player2_prereq": 269710641,
        "player2_greenroom": 0,
        "winner": "Caldera",
        "loser": "Wreckfest",
        "updated_at": 1648336774,
        "underway": 0,
        "player1_lastFought": 1648329049,
        "player2_lastFought": 1648334588
    },
    "131": {
        "id": 269710650,
        "order": 131,
        "state": "complete",
        "round": -5,
        "player1": "Red Hawk",
        "player2": "Djem So",
        "player1_id": 166697906,
        "player1_greenroom": 0,
        "player1_prereq": 269710575,
        "player2_id": 166697924,
        "player2_prereq": 269710642,
        "player2_greenroom": 0,
        "winner": "Djem So",
        "loser": "Red Hawk",
        "updated_at": 1648341164,
        "underway": 0,
        "player1_lastFought": 1648326456,
        "player2_lastFought": 1648337503
    },
    "132": {
        "id": 269710651,
        "order": 132,
        "state": "complete",
        "round": -5,
        "player1": "Sepi01",
        "player2": "Jet Lag",
        "player1_id": 166697915,
        "player1_greenroom": 0,
        "player1_prereq": 269710576,
        "player2_id": 166697918,
        "player2_prereq": 269710643,
        "player2_greenroom": 0,
        "winner": "Sepi01",
        "loser": "Jet Lag",
        "updated_at": 1648338331,
        "underway": 0,
        "player1_lastFought": 1648330376,
        "player2_lastFought": 1648335694
    },
    "139": {
        "id": 269710652,
        "order": 139,
        "state": "complete",
        "round": -6,
        "player1": "Narcissist",
        "player2": "Spartan X",
        "player1_id": 166697975,
        "player1_greenroom": 0,
        "player1_prereq": 269710644,
        "player2_id": 166697920,
        "player2_prereq": 269710645,
        "player2_greenroom": 0,
        "winner": "Narcissist",
        "loser": "Spartan X",
        "updated_at": 1648339750,
        "underway": 0,
        "player1_lastFought": 1648336323,
        "player2_lastFought": 1648335653
    },
    "140": {
        "id": 269710653,
        "order": 140,
        "state": "complete",
        "round": -6,
        "player1": "Blackbird",
        "player2": "Tothik",
        "player1_id": 166697912,
        "player1_greenroom": 0,
        "player1_prereq": 269710646,
        "player2_id": 166697923,
        "player2_prereq": 269710647,
        "player2_greenroom": 0,
        "winner": "Tothik",
        "loser": "Blackbird",
        "updated_at": 1648343394,
        "underway": 0,
        "player1_lastFought": 1648334080,
        "player2_lastFought": 1648340437
    },
    "137": {
        "id": 269710654,
        "order": 137,
        "state": "complete",
        "round": -6,
        "player1": "Silent Spring",
        "player2": "Caldera",
        "player1_id": 166697905,
        "player1_greenroom": 0,
        "player1_prereq": 269710648,
        "player2_id": 166697911,
        "player2_prereq": 269710649,
        "player2_greenroom": 0,
        "winner": "Silent Spring",
        "loser": "Caldera",
        "updated_at": 1648339991,
        "underway": 0,
        "player1_lastFought": 1648338220,
        "player2_lastFought": 1648336774
    },
    "138": {
        "id": 269710655,
        "order": 138,
        "state": "complete",
        "round": -6,
        "player1": "Djem So",
        "player2": "Sepi01",
        "player1_id": 166697924,
        "player1_greenroom": 0,
        "player1_prereq": 269710650,
        "player2_id": 166697915,
        "player2_prereq": 269710651,
        "player2_greenroom": 0,
        "winner": "Sepi01",
        "loser": "Djem So",
        "updated_at": 1648343803,
        "underway": 0,
        "player1_lastFought": 1648341164,
        "player2_lastFought": 1648338331
    },
    "145": {
        "id": 269710656,
        "order": 145,
        "state": "complete",
        "round": -7,
        "player1": "Starchild",
        "player2": "Narcissist",
        "player1_id": 166697910,
        "player1_greenroom": 0,
        "player1_prereq": 269710581,
        "player2_id": 166697975,
        "player2_prereq": 269710652,
        "player2_greenroom": 0,
        "winner": "Narcissist",
        "loser": "Starchild",
        "updated_at": 1648342887,
        "underway": 0,
        "player1_lastFought": 1648334154,
        "player2_lastFought": 1648339750
    },
    "146": {
        "id": 269710657,
        "order": 146,
        "state": "complete",
        "round": -7,
        "player1": "Jack Move",
        "player2": "Tothik",
        "player1_id": 166697921,
        "player1_greenroom": 0,
        "player1_prereq": 269710582,
        "player2_id": 166697923,
        "player2_prereq": 269710653,
        "player2_greenroom": 0,
        "winner": "Jack Move",
        "loser": "Tothik",
        "updated_at": 1648345888,
        "underway": 0,
        "player1_lastFought": 1648337214,
        "player2_lastFought": 1648343394
    },
    "147": {
        "id": 269710658,
        "order": 147,
        "state": "complete",
        "round": -7,
        "player1": "Weta X",
        "player2": "Silent Spring",
        "player1_id": 166697965,
        "player1_greenroom": 0,
        "player1_prereq": 269710583,
        "player2_id": 166697905,
        "player2_prereq": 269710654,
        "player2_greenroom": 0,
        "winner": "Silent Spring",
        "loser": "Weta X",
        "updated_at": 1648343538,
        "underway": 0,
        "player1_lastFought": 1648336450,
        "player2_lastFought": 1648339991
    },
    "148": {
        "id": 269710659,
        "order": 148,
        "state": "complete",
        "round": -7,
        "player1": "Clyde",
        "player2": "Sepi01",
        "player1_id": 166697938,
        "player1_greenroom": 0,
        "player1_prereq": 269710584,
        "player2_id": 166697915,
        "player2_prereq": 269710655,
        "player2_greenroom": 0,
        "winner": "Sepi01",
        "loser": "Clyde",
        "updated_at": 1648345000,
        "underway": 0,
        "player1_lastFought": 1648338850,
        "player2_lastFought": 1648343803
    },
    "149": {
        "id": 269710660,
        "order": 149,
        "state": "complete",
        "round": -8,
        "player1": "Narcissist",
        "player2": "Jack Move",
        "player1_id": 166697975,
        "player1_greenroom": 0,
        "player1_prereq": 269710656,
        "player2_id": 166697921,
        "player2_prereq": 269710657,
        "player2_greenroom": 0,
        "winner": "Narcissist",
        "loser": "Jack Move",
        "updated_at": 1648349248,
        "underway": 0,
        "player1_lastFought": 1648342887,
        "player2_lastFought": 1648345888
    },
    "150": {
        "id": 269710661,
        "order": 150,
        "state": "complete",
        "round": -8,
        "player1": "Silent Spring",
        "player2": "Sepi01",
        "player1_id": 166697905,
        "player1_greenroom": 0,
        "player1_prereq": 269710658,
        "player2_id": 166697915,
        "player2_prereq": 269710659,
        "player2_greenroom": 0,
        "winner": "Silent Spring",
        "loser": "Sepi01",
        "updated_at": 1648347012,
        "underway": 0,
        "player1_lastFought": 1648343538,
        "player2_lastFought": 1648345000
    },
    "154": {
        "id": 269710662,
        "order": 154,
        "state": "complete",
        "round": -9,
        "player1": "Adrift",
        "player2": "Narcissist",
        "player1_id": 166697916,
        "player1_greenroom": 0,
        "player1_prereq": 269710586,
        "player2_id": 166697975,
        "player2_prereq": 269710660,
        "player2_greenroom": 0,
        "winner": "Narcissist",
        "loser": "Adrift",
        "updated_at": 1648351257,
        "underway": 0,
        "player1_lastFought": 1648341923,
        "player2_lastFought": 1648349248
    },
    "153": {
        "id": 269710663,
        "order": 153,
        "state": "complete",
        "round": -9,
        "player1": "Sea Dragons Roar",
        "player2": "Silent Spring",
        "player1_id": 166697948,
        "player1_greenroom": 0,
        "player1_prereq": 269710585,
        "player2_id": 166697905,
        "player2_prereq": 269710661,
        "player2_greenroom": 0,
        "winner": "Silent Spring",
        "loser": "Sea Dragons Roar",
        "updated_at": 1648350899,
        "underway": 0,
        "player1_lastFought": 1648339599,
        "player2_lastFought": 1648347012
    },
    "155": {
        "id": 269710664,
        "order": 155,
        "state": "complete",
        "round": -10,
        "player1": "Narcissist",
        "player2": "Silent Spring",
        "player1_id": 166697975,
        "player1_greenroom": 0,
        "player1_prereq": 269710662,
        "player2_id": 166697905,
        "player2_prereq": 269710663,
        "player2_greenroom": 0,
        "winner": "Silent Spring",
        "loser": "Narcissist",
        "updated_at": 1648353204,
        "underway": 0,
        "player1_lastFought": 1648351257,
        "player2_lastFought": 1648350899
    },
    "157": {
        "id": 269710665,
        "order": 157,
        "state": "complete",
        "round": -11,
        "player1": "Silk",
        "player2": "Silent Spring",
        "player1_id": 166697907,
        "player1_greenroom": 0,
        "player1_prereq": 269710587,
        "player2_id": 166697905,
        "player2_prereq": 269710664,
        "player2_greenroom": 0,
        "winner": "Silent Spring",
        "loser": "Silk",
        "updated_at": 1648354241,
        "underway": 0,
        "player1_lastFought": 1648346798,
        "player2_lastFought": 1648353204
    },
    "158": {
        "id": 269710666,
        "order": 158,
        "state": "complete",
        "round": 8,
        "player1": "Stoneforge",
        "player2": "Silent Spring",
        "player1_id": 166697922,
        "player1_greenroom": 0,
        "player1_prereq": 269710587,
        "player2_id": 166697905,
        "player2_prereq": 269710665,
        "player2_greenroom": 0,
        "winner": "Silent Spring",
        "loser": "Stoneforge",
        "updated_at": 1648355176,
        "underway": 0,
        "player1_lastFought": 1648346798,
        "player2_lastFought": 1648354241
    },
    "159": {
        "id": 269710667,
        "order": 159,
        "state": "complete",
        "round": 8,
        "player1": "Silent Spring",
        "player2": "Stoneforge",
        "player1_id": 166697905,
        "player1_greenroom": 0,
        "player1_prereq": 269710666,
        "player2_id": 166697922,
        "player2_prereq": 269710666,
        "player2_greenroom": 0,
        "winner": "Silent Spring",
        "loser": "Stoneforge",
        "updated_at": 1648356587,
        "underway": 0,
        "player1_lastFought": 1648355176,
        "player2_lastFought": 1648355176
    }
}